{
    "gameId": "0022300376",
    "gameCode": "20231221/SASCHI",
    "gameStatus": 3,
    "gameStatusText": "Final",
    "period": 4,
    "gameClock": "PT00M00.00S",
    "gameTimeUTC": "2023-12-22T01:00:00Z",
    "gameEt": "2023-12-21T20:00:00Z",
    "awayTeamId": 1610612759,
    "homeTeamId": 1610612741,
    "duration": "2:02",
    "attendance": 20697,
    "sellout": 0,
    "seriesGameNumber": "",
    "gameLabel": "",
    "gameSubLabel": "",
    "seriesText": "",
    "ifNecessary": false,
    "arena": {
        "arenaId": 66,
        "arenaName": "United Center",
        "arenaCity": "Chicago",
        "arenaState": "IL",
        "arenaCountry": "US",
        "arenaTimezone": "Central",
        "arenaStreetAddress": "",
        "arenaPostalCode": ""
    },
    "officials": [
        {
            "personId": 2005,
            "name": "Matt Boland",
            "nameI": "M. Boland",
            "firstName": "Matt",
            "familyName": "Boland",
            "jerseyNum": "18  ",
            "assignment": ""
        },
        {
            "personId": 202026,
            "name": "Karl Lane",
            "nameI": "K. Lane",
            "firstName": "Karl",
            "familyName": "Lane",
            "jerseyNum": "77  ",
            "assignment": ""
        },
        {
            "personId": 1626302,
            "name": "Aaron Smith",
            "nameI": "A. Smith",
            "firstName": "Aaron",
            "familyName": "Smith",
            "jerseyNum": "51  ",
            "assignment": ""
        }
    ],
    "broadcasters": {
        "nationalBroadcasters": [],
        "nationalRadioBroadcasters": [
            {
                "broadcasterId": 1001098,
                "broadcastDisplay": "SiriusXM",
                "broadcasterDisplay": "SiriusXM",
                "broadcasterVideoLink": "https://www.siriusxm.com/sports/nba?utm_campaign=SXM_NA_BAU&utm_source=2023-11_NA_NBA-SiriusXMNFLRadio.NBA.NBAWebsiteWaystoListen.NA.Logo-NBA2023WaystoListen.Q42023.NA&utm_medium=Partner&utm_term=",
                "broadcasterDescription": null,
                "broadcasterTeamId": -1
            }
        ],
        "nationalOttBroadcasters": [],
        "homeTvBroadcasters": [
            {
                "broadcasterId": 1656,
                "broadcastDisplay": "NBCSCH",
                "broadcasterDisplay": "NBC Sports Chicago",
                "broadcasterVideoLink": "http://stream.nbcsports.com/rsn/nba-bulls-live-stream",
                "broadcasterDescription": null,
                "broadcasterTeamId": 1610612741
            }
        ],
        "homeRadioBroadcasters": [
            {
                "broadcasterId": 1688,
                "broadcastDisplay": "WSCR/WRTO",
                "broadcasterDisplay": "670 AM / S: 1200 AM",
                "broadcasterVideoLink": "",
                "broadcasterDescription": null,
                "broadcasterTeamId": 1610612741
            }
        ],
        "homeOttBroadcasters": [],
        "awayTvBroadcasters": [
            {
                "broadcasterId": 1000344,
                "broadcastDisplay": "BSSW-SA",
                "broadcasterDisplay": "Bally Sports SW-SA",
                "broadcasterVideoLink": "",
                "broadcasterDescription": null,
                "broadcasterTeamId": 1610612759
            }
        ],
        "awayRadioBroadcasters": [
            {
                "broadcasterId": 1000260,
                "broadcastDisplay": "WOAI/KXTN",
                "broadcasterDisplay": "WOAI/KXTN",
                "broadcasterVideoLink": "",
                "broadcasterDescription": null,
                "broadcasterTeamId": 1610612759
            }
        ],
        "awayOttBroadcasters": []
    },
    "homeTeam": {
        "teamId": 1610612741,
        "teamName": "Bulls",
        "teamCity": "Chicago",
        "teamTricode": "CHI",
        "teamSlug": "bulls",
        "teamWins": 13,
        "teamLosses": 17,
        "score": 114,
        "inBonus": "",
        "timeoutsRemaining": 0,
        "seed": 0,
        "statistics": {
            "minutes": "240:00",
            "fieldGoalsMade": 49,
            "fieldGoalsAttempted": 90,
            "fieldGoalsPercentage": 0.544,
            "threePointersMade": 7,
            "threePointersAttempted": 28,
            "threePointersPercentage": 0.25,
            "freeThrowsMade": 9,
            "freeThrowsAttempted": 11,
            "freeThrowsPercentage": 0.818,
            "reboundsOffensive": 5,
            "reboundsDefensive": 31,
            "reboundsTotal": 36,
            "assists": 24,
            "steals": 11,
            "blocks": 5,
            "turnovers": 11,
            "foulsPersonal": 18,
            "points": 114,
            "plusMinusPoints": 19
        },
        "periods": [
            {
                "period": 1,
                "periodType": "REGULAR",
                "score": 27
            },
            {
                "period": 2,
                "periodType": "REGULAR",
                "score": 25
            },
            {
                "period": 3,
                "periodType": "REGULAR",
                "score": 25
            },
            {
                "period": 4,
                "periodType": "REGULAR",
                "score": 37
            }
        ],
        "players": [
            {
                "personId": 201942,
                "firstName": "DeMar",
                "familyName": "DeRozan",
                "nameI": "D. DeRozan",
                "playerSlug": "demar-derozan",
                "position": "F",
                "comment": "",
                "jerseyNum": "",
                "statistics": {
                    "minutes": "35:55",
                    "fieldGoalsMade": 9,
                    "fieldGoalsAttempted": 15,
                    "fieldGoalsPercentage": 0.6,
                    "threePointersMade": 1,
                    "threePointersAttempted": 3,
                    "threePointersPercentage": 0.333,
                    "freeThrowsMade": 2,
                    "freeThrowsAttempted": 2,
                    "freeThrowsPercentage": 1,
                    "reboundsOffensive": 0,
                    "reboundsDefensive": 4,
                    "reboundsTotal": 4,
                    "assists": 5,
                    "steals": 0,
                    "blocks": 1,
                    "turnovers": 0,
                    "foulsPersonal": 1,
                    "points": 21,
                    "plusMinusPoints": 10
                }
            },
            {
                "personId": 1630172,
                "firstName": "Patrick",
                "familyName": "Williams",
                "nameI": "P. Williams",
                "playerSlug": "patrick-williams",
                "position": "F",
                "comment": "",
                "jerseyNum": "",
                "statistics": {
                    "minutes": "30:53",
                    "fieldGoalsMade": 7,
                    "fieldGoalsAttempted": 11,
                    "fieldGoalsPercentage": 0.636,
                    "threePointersMade": 2,
                    "threePointersAttempted": 4,
                    "threePointersPercentage": 0.5,
                    "freeThrowsMade": 2,
                    "freeThrowsAttempted": 2,
                    "freeThrowsPercentage": 1,
                    "reboundsOffensive": 0,
                    "reboundsDefensive": 4,
                    "reboundsTotal": 4,
                    "assists": 2,
                    "steals": 1,
                    "blocks": 1,
                    "turnovers": 2,
                    "foulsPersonal": 2,
                    "points": 18,
                    "plusMinusPoints": 15
                }
            },
            {
                "personId": 202696,
                "firstName": "Nikola",
                "familyName": "Vu\u010devi\u0107",
                "nameI": "N. Vu\u010devi\u0107",
                "playerSlug": "nikola-vu\u010devi\u0107",
                "position": "C",
                "comment": "",
                "jerseyNum": "",
                "statistics": {
                    "minutes": "26:36",
                    "fieldGoalsMade": 8,
                    "fieldGoalsAttempted": 19,
                    "fieldGoalsPercentage": 0.421,
                    "threePointersMade": 0,
                    "threePointersAttempted": 7,
                    "threePointersPercentage": 0,
                    "freeThrowsMade": 0,
                    "freeThrowsAttempted": 0,
                    "freeThrowsPercentage": 0,
                    "reboundsOffensive": 1,
                    "reboundsDefensive": 4,
                    "reboundsTotal": 5,
                    "assists": 3,
                    "steals": 1,
                    "blocks": 0,
                    "turnovers": 2,
                    "foulsPersonal": 2,
                    "points": 16,
                    "plusMinusPoints": 3
                }
            },
            {
                "personId": 1627936,
                "firstName": "Alex",
                "familyName": "Caruso",
                "nameI": "A. Caruso",
                "playerSlug": "alex-caruso",
                "position": "G",
                "comment": "",
                "jerseyNum": "",
                "statistics": {
                    "minutes": "21:42",
                    "fieldGoalsMade": 4,
                    "fieldGoalsAttempted": 6,
                    "fieldGoalsPercentage": 0.667,
                    "threePointersMade": 0,
                    "threePointersAttempted": 0,
                    "threePointersPercentage": 0,
                    "freeThrowsMade": 0,
                    "freeThrowsAttempted": 0,
                    "freeThrowsPercentage": 0,
                    "reboundsOffensive": 0,
                    "reboundsDefensive": 3,
                    "reboundsTotal": 3,
                    "assists": 3,
                    "steals": 3,
                    "blocks": 0,
                    "turnovers": 2,
                    "foulsPersonal": 5,
                    "points": 8,
                    "plusMinusPoints": 10
                }
            },
            {
                "personId": 1629632,
                "firstName": "Coby",
                "familyName": "White",
                "nameI": "C. White",
                "playerSlug": "coby-white",
                "position": "G",
                "comment": "",
                "jerseyNum": "",
                "statistics": {
                    "minutes": "36:14",
                    "fieldGoalsMade": 10,
                    "fieldGoalsAttempted": 15,
                    "fieldGoalsPercentage": 0.667,
                    "threePointersMade": 2,
                    "threePointersAttempted": 6,
                    "threePointersPercentage": 0.333,
                    "freeThrowsMade": 0,
                    "freeThrowsAttempted": 0,
                    "freeThrowsPercentage": 0,
                    "reboundsOffensive": 0,
                    "reboundsDefensive": 6,
                    "reboundsTotal": 6,
                    "assists": 5,
                    "steals": 0,
                    "blocks": 0,
                    "turnovers": 3,
                    "foulsPersonal": 2,
                    "points": 22,
                    "plusMinusPoints": 9
                }
            },
            {
                "personId": 1630245,
                "firstName": "Ayo",
                "familyName": "Dosunmu",
                "nameI": "A. Dosunmu",
                "playerSlug": "ayo-dosunmu",
                "position": "",
                "comment": "",
                "jerseyNum": "",
                "statistics": {
                    "minutes": "26:23",
                    "fieldGoalsMade": 5,
                    "fieldGoalsAttempted": 8,
                    "fieldGoalsPercentage": 0.625,
                    "threePointersMade": 1,
                    "threePointersAttempted": 4,
                    "threePointersPercentage": 0.25,
                    "freeThrowsMade": 0,
                    "freeThrowsAttempted": 0,
                    "freeThrowsPercentage": 0,
                    "reboundsOffensive": 0,
                    "reboundsDefensive": 2,
                    "reboundsTotal": 2,
                    "assists": 0,
                    "steals": 1,
                    "blocks": 0,
                    "turnovers": 0,
                    "foulsPersonal": 2,
                    "points": 11,
                    "plusMinusPoints": 13
                }
            },
            {
                "personId": 203083,
                "firstName": "Andre",
                "familyName": "Drummond",
                "nameI": "A. Drummond",
                "playerSlug": "andre-drummond",
                "position": "",
                "comment": "",
                "jerseyNum": "",
                "statistics": {
                    "minutes": "19:00",
                    "fieldGoalsMade": 5,
                    "fieldGoalsAttempted": 10,
                    "fieldGoalsPercentage": 0.5,
                    "threePointersMade": 0,
                    "threePointersAttempted": 0,
                    "threePointersPercentage": 0,
                    "freeThrowsMade": 2,
                    "freeThrowsAttempted": 3,
                    "freeThrowsPercentage": 0.667,
                    "reboundsOffensive": 4,
                    "reboundsDefensive": 4,
                    "reboundsTotal": 8,
                    "assists": 1,
                    "steals": 5,
                    "blocks": 2,
                    "turnovers": 1,
                    "foulsPersonal": 0,
                    "points": 12,
                    "plusMinusPoints": 17
                }
            },
            {
                "personId": 1641763,
                "firstName": "Julian",
                "familyName": "Phillips",
                "nameI": "J. Phillips",
                "playerSlug": "julian-phillips",
                "position": "",
                "comment": "",
                "jerseyNum": "",
                "statistics": {
                    "minutes": "4:12",
                    "fieldGoalsMade": 0,
                    "fieldGoalsAttempted": 1,
                    "fieldGoalsPercentage": 0,
                    "threePointersMade": 0,
                    "threePointersAttempted": 1,
                    "threePointersPercentage": 0,
                    "freeThrowsMade": 0,
                    "freeThrowsAttempted": 0,
                    "freeThrowsPercentage": 0,
                    "reboundsOffensive": 0,
                    "reboundsDefensive": 0,
                    "reboundsTotal": 0,
                    "assists": 0,
                    "steals": 0,
                    "blocks": 0,
                    "turnovers": 0,
                    "foulsPersonal": 1,
                    "points": 0,
                    "plusMinusPoints": -5
                }
            },
            {
                "personId": 1631207,
                "firstName": "Dalen",
                "familyName": "Terry",
                "nameI": "D. Terry",
                "playerSlug": "dalen-terry",
                "position": "",
                "comment": "",
                "jerseyNum": "",
                "statistics": {
                    "minutes": "17:29",
                    "fieldGoalsMade": 0,
                    "fieldGoalsAttempted": 2,
                    "fieldGoalsPercentage": 0,
                    "threePointersMade": 0,
                    "threePointersAttempted": 2,
                    "threePointersPercentage": 0,
                    "freeThrowsMade": 1,
                    "freeThrowsAttempted": 2,
                    "freeThrowsPercentage": 0.5,
                    "reboundsOffensive": 0,
                    "reboundsDefensive": 3,
                    "reboundsTotal": 3,
                    "assists": 3,
                    "steals": 0,
                    "blocks": 0,
                    "turnovers": 0,
                    "foulsPersonal": 1,
                    "points": 1,
                    "plusMinusPoints": 11
                }
            },
            {
                "personId": 1628975,
                "firstName": "Jevon",
                "familyName": "Carter",
                "nameI": "J. Carter",
                "playerSlug": "jevon-carter",
                "position": "",
                "comment": "",
                "jerseyNum": "",
                "statistics": {
                    "minutes": "19:12",
                    "fieldGoalsMade": 1,
                    "fieldGoalsAttempted": 3,
                    "fieldGoalsPercentage": 0.333,
                    "threePointersMade": 1,
                    "threePointersAttempted": 1,
                    "threePointersPercentage": 1,
                    "freeThrowsMade": 2,
                    "freeThrowsAttempted": 2,
                    "freeThrowsPercentage": 1,
                    "reboundsOffensive": 0,
                    "reboundsDefensive": 1,
                    "reboundsTotal": 1,
                    "assists": 2,
                    "steals": 0,
                    "blocks": 1,
                    "turnovers": 0,
                    "foulsPersonal": 1,
                    "points": 5,
                    "plusMinusPoints": 13
                }
            },
            {
                "personId": 1630678,
                "firstName": "Terry",
                "familyName": "Taylor",
                "nameI": "T. Taylor",
                "playerSlug": "terry-taylor",
                "position": "",
                "comment": "",
                "jerseyNum": "",
                "statistics": {
                    "minutes": "2:24",
                    "fieldGoalsMade": 0,
                    "fieldGoalsAttempted": 0,
                    "fieldGoalsPercentage": 0,
                    "threePointersMade": 0,
                    "threePointersAttempted": 0,
                    "threePointersPercentage": 0,
                    "freeThrowsMade": 0,
                    "freeThrowsAttempted": 0,
                    "freeThrowsPercentage": 0,
                    "reboundsOffensive": 0,
                    "reboundsDefensive": 0,
                    "reboundsTotal": 0,
                    "assists": 0,
                    "steals": 0,
                    "blocks": 0,
                    "turnovers": 1,
                    "foulsPersonal": 1,
                    "points": 0,
                    "plusMinusPoints": -1
                }
            },
            {
                "personId": 1628470,
                "firstName": "Torrey",
                "familyName": "Craig",
                "nameI": "T. Craig",
                "playerSlug": "torrey-craig",
                "position": "",
                "comment": "DND - Injury/Illness",
                "jerseyNum": "",
                "statistics": {
                    "minutes": "",
                    "fieldGoalsMade": 0,
                    "fieldGoalsAttempted": 0,
                    "fieldGoalsPercentage": 0,
                    "threePointersMade": 0,
                    "threePointersAttempted": 0,
                    "threePointersPercentage": 0,
                    "freeThrowsMade": 0,
                    "freeThrowsAttempted": 0,
                    "freeThrowsPercentage": 0,
                    "reboundsOffensive": 0,
                    "reboundsDefensive": 0,
                    "reboundsTotal": 0,
                    "assists": 0,
                    "steals": 0,
                    "blocks": 0,
                    "turnovers": 0,
                    "foulsPersonal": 0,
                    "points": 0,
                    "plusMinusPoints": 0
                }
            }
        ],
        "inactives": [
            {
                "personId": 1628366,
                "firstName": "Lonzo",
                "familyName": "Ball",
                "jerseyNum": "2   "
            },
            {
                "personId": 203897,
                "firstName": "Zach",
                "familyName": "LaVine",
                "jerseyNum": "8   "
            },
            {
                "personId": 1630929,
                "firstName": "Henri",
                "familyName": "Drell",
                "jerseyNum": "77  "
            },
            {
                "personId": 1641766,
                "firstName": "Adama",
                "familyName": "Sanogo",
                "jerseyNum": "21  "
            },
            {
                "personId": 1641931,
                "firstName": "Onuralp",
                "familyName": "Bitim",
                "jerseyNum": "17  "
            }
        ],
        "starters": {
            "minutes": "151:20",
            "fieldGoalsMade": 38,
            "fieldGoalsAttempted": 66,
            "fieldGoalsPercentage": 0.576,
            "threePointersMade": 5,
            "threePointersAttempted": 20,
            "threePointersPercentage": 0.25,
            "freeThrowsMade": 4,
            "freeThrowsAttempted": 4,
            "freeThrowsPercentage": 1,
            "reboundsOffensive": 1,
            "reboundsDefensive": 21,
            "reboundsTotal": 22,
            "assists": 18,
            "steals": 5,
            "blocks": 2,
            "turnovers": 9,
            "foulsPersonal": 12,
            "points": 85
        },
        "bench": {
            "minutes": "151:20",
            "fieldGoalsMade": 6,
            "fieldGoalsAttempted": 15,
            "fieldGoalsPercentage": 0.4,
            "threePointersMade": 1,
            "threePointersAttempted": 3,
            "threePointersPercentage": 0.333,
            "freeThrowsMade": 5,
            "freeThrowsAttempted": 7,
            "freeThrowsPercentage": 0.714,
            "reboundsOffensive": 4,
            "reboundsDefensive": 8,
            "reboundsTotal": 12,
            "assists": 6,
            "steals": 5,
            "blocks": 3,
            "turnovers": 2,
            "foulsPersonal": 3,
            "points": 18
        }
    },
    "awayTeam": {
        "teamId": 1610612759,
        "teamName": "Spurs",
        "teamCity": "San Antonio",
        "teamTricode": "SAS",
        "teamSlug": "spurs",
        "teamWins": 4,
        "teamLosses": 23,
        "score": 95,
        "inBonus": "",
        "timeoutsRemaining": 1,
        "seed": 0,
        "statistics": {
            "minutes": "240:00",
            "fieldGoalsMade": 37,
            "fieldGoalsAttempted": 81,
            "fieldGoalsPercentage": 0.457,
            "threePointersMade": 10,
            "threePointersAttempted": 30,
            "threePointersPercentage": 0.333,
            "freeThrowsMade": 11,
            "freeThrowsAttempted": 16,
            "freeThrowsPercentage": 0.688,
            "reboundsOffensive": 9,
            "reboundsDefensive": 32,
            "reboundsTotal": 41,
            "assists": 24,
            "steals": 6,
            "blocks": 7,
            "turnovers": 19,
            "foulsPersonal": 11,
            "points": 95,
            "plusMinusPoints": -19
        },
        "periods": [
            {
                "period": 1,
                "periodType": "REGULAR",
                "score": 28
            },
            {
                "period": 2,
                "periodType": "REGULAR",
                "score": 20
            },
            {
                "period": 3,
                "periodType": "REGULAR",
                "score": 22
            },
            {
                "period": 4,
                "periodType": "REGULAR",
                "score": 25
            }
        ],
        "players": [
            {
                "personId": 1631110,
                "firstName": "Jeremy",
                "familyName": "Sochan",
                "nameI": "J. Sochan",
                "playerSlug": "jeremy-sochan",
                "position": "F",
                "comment": "",
                "jerseyNum": "",
                "statistics": {
                    "minutes": "33:59",
                    "fieldGoalsMade": 4,
                    "fieldGoalsAttempted": 8,
                    "fieldGoalsPercentage": 0.5,
                    "threePointersMade": 1,
                    "threePointersAttempted": 2,
                    "threePointersPercentage": 0.5,
                    "freeThrowsMade": 0,
                    "freeThrowsAttempted": 0,
                    "freeThrowsPercentage": 0,
                    "reboundsOffensive": 3,
                    "reboundsDefensive": 4,
                    "reboundsTotal": 7,
                    "assists": 2,
                    "steals": 1,
                    "blocks": 0,
                    "turnovers": 1,
                    "foulsPersonal": 0,
                    "points": 9,
                    "plusMinusPoints": -12
                }
            },
            {
                "personId": 1629640,
                "firstName": "Keldon",
                "familyName": "Johnson",
                "nameI": "K. Johnson",
                "playerSlug": "keldon-johnson",
                "position": "F",
                "comment": "",
                "jerseyNum": "",
                "statistics": {
                    "minutes": "32:19",
                    "fieldGoalsMade": 5,
                    "fieldGoalsAttempted": 13,
                    "fieldGoalsPercentage": 0.385,
                    "threePointersMade": 0,
                    "threePointersAttempted": 2,
                    "threePointersPercentage": 0,
                    "freeThrowsMade": 1,
                    "freeThrowsAttempted": 3,
                    "freeThrowsPercentage": 0.333,
                    "reboundsOffensive": 2,
                    "reboundsDefensive": 4,
                    "reboundsTotal": 6,
                    "assists": 2,
                    "steals": 0,
                    "blocks": 0,
                    "turnovers": 3,
                    "foulsPersonal": 3,
                    "points": 11,
                    "plusMinusPoints": -10
                }
            },
            {
                "personId": 1641705,
                "firstName": "Victor",
                "familyName": "Wembanyama",
                "nameI": "V. Wembanyama",
                "playerSlug": "victor-wembanyama",
                "position": "C",
                "comment": "",
                "jerseyNum": "",
                "statistics": {
                    "minutes": "22:13",
                    "fieldGoalsMade": 3,
                    "fieldGoalsAttempted": 8,
                    "fieldGoalsPercentage": 0.375,
                    "threePointersMade": 0,
                    "threePointersAttempted": 1,
                    "threePointersPercentage": 0,
                    "freeThrowsMade": 1,
                    "freeThrowsAttempted": 3,
                    "freeThrowsPercentage": 0.333,
                    "reboundsOffensive": 0,
                    "reboundsDefensive": 5,
                    "reboundsTotal": 5,
                    "assists": 5,
                    "steals": 2,
                    "blocks": 3,
                    "turnovers": 2,
                    "foulsPersonal": 0,
                    "points": 7,
                    "plusMinusPoints": -7
                }
            },
            {
                "personId": 1630170,
                "firstName": "Devin",
                "familyName": "Vassell",
                "nameI": "D. Vassell",
                "playerSlug": "devin-vassell",
                "position": "G",
                "comment": "",
                "jerseyNum": "",
                "statistics": {
                    "minutes": "31:22",
                    "fieldGoalsMade": 7,
                    "fieldGoalsAttempted": 15,
                    "fieldGoalsPercentage": 0.467,
                    "threePointersMade": 3,
                    "threePointersAttempted": 8,
                    "threePointersPercentage": 0.375,
                    "freeThrowsMade": 4,
                    "freeThrowsAttempted": 4,
                    "freeThrowsPercentage": 1,
                    "reboundsOffensive": 1,
                    "reboundsDefensive": 3,
                    "reboundsTotal": 4,
                    "assists": 2,
                    "steals": 1,
                    "blocks": 0,
                    "turnovers": 1,
                    "foulsPersonal": 0,
                    "points": 21,
                    "plusMinusPoints": -4
                }
            },
            {
                "personId": 1631103,
                "firstName": "Malaki",
                "familyName": "Branham",
                "nameI": "M. Branham",
                "playerSlug": "malaki-branham",
                "position": "G",
                "comment": "",
                "jerseyNum": "",
                "statistics": {
                    "minutes": "29:16",
                    "fieldGoalsMade": 6,
                    "fieldGoalsAttempted": 11,
                    "fieldGoalsPercentage": 0.545,
                    "threePointersMade": 1,
                    "threePointersAttempted": 4,
                    "threePointersPercentage": 0.25,
                    "freeThrowsMade": 0,
                    "freeThrowsAttempted": 0,
                    "freeThrowsPercentage": 0,
                    "reboundsOffensive": 0,
                    "reboundsDefensive": 6,
                    "reboundsTotal": 6,
                    "assists": 2,
                    "steals": 0,
                    "blocks": 0,
                    "turnovers": 3,
                    "foulsPersonal": 1,
                    "points": 13,
                    "plusMinusPoints": -4
                }
            },
            {
                "personId": 1628380,
                "firstName": "Zach",
                "familyName": "Collins",
                "nameI": "Z. Collins",
                "playerSlug": "zach-collins",
                "position": "",
                "comment": "",
                "jerseyNum": "",
                "statistics": {
                    "minutes": "27:50",
                    "fieldGoalsMade": 5,
                    "fieldGoalsAttempted": 10,
                    "fieldGoalsPercentage": 0.5,
                    "threePointersMade": 2,
                    "threePointersAttempted": 4,
                    "threePointersPercentage": 0.5,
                    "freeThrowsMade": 2,
                    "freeThrowsAttempted": 2,
                    "freeThrowsPercentage": 1,
                    "reboundsOffensive": 3,
                    "reboundsDefensive": 6,
                    "reboundsTotal": 9,
                    "assists": 2,
                    "steals": 0,
                    "blocks": 3,
                    "turnovers": 1,
                    "foulsPersonal": 2,
                    "points": 14,
                    "plusMinusPoints": -20
                }
            },
            {
                "personId": 1630200,
                "firstName": "Tre",
                "familyName": "Jones",
                "nameI": "T. Jones",
                "playerSlug": "tre-jones",
                "position": "",
                "comment": "",
                "jerseyNum": "",
                "statistics": {
                    "minutes": "21:01",
                    "fieldGoalsMade": 4,
                    "fieldGoalsAttempted": 6,
                    "fieldGoalsPercentage": 0.667,
                    "threePointersMade": 1,
                    "threePointersAttempted": 1,
                    "threePointersPercentage": 1,
                    "freeThrowsMade": 0,
                    "freeThrowsAttempted": 0,
                    "freeThrowsPercentage": 0,
                    "reboundsOffensive": 0,
                    "reboundsDefensive": 1,
                    "reboundsTotal": 1,
                    "assists": 3,
                    "steals": 1,
                    "blocks": 0,
                    "turnovers": 5,
                    "foulsPersonal": 0,
                    "points": 9,
                    "plusMinusPoints": -11
                }
            },
            {
                "personId": 1626224,
                "firstName": "Cedi",
                "familyName": "Osman",
                "nameI": "C. Osman",
                "playerSlug": "cedi-osman",
                "position": "",
                "comment": "",
                "jerseyNum": "",
                "statistics": {
                    "minutes": "11:14",
                    "fieldGoalsMade": 0,
                    "fieldGoalsAttempted": 4,
                    "fieldGoalsPercentage": 0,
                    "threePointersMade": 0,
                    "threePointersAttempted": 3,
                    "threePointersPercentage": 0,
                    "freeThrowsMade": 2,
                    "freeThrowsAttempted": 2,
                    "freeThrowsPercentage": 1,
                    "reboundsOffensive": 0,
                    "reboundsDefensive": 1,
                    "reboundsTotal": 1,
                    "assists": 3,
                    "steals": 0,
                    "blocks": 0,
                    "turnovers": 2,
                    "foulsPersonal": 1,
                    "points": 2,
                    "plusMinusPoints": -12
                }
            },
            {
                "personId": 203926,
                "firstName": "Doug",
                "familyName": "McDermott",
                "nameI": "D. McDermott",
                "playerSlug": "doug-mcdermott",
                "position": "",
                "comment": "",
                "jerseyNum": "",
                "statistics": {
                    "minutes": "11:33",
                    "fieldGoalsMade": 1,
                    "fieldGoalsAttempted": 4,
                    "fieldGoalsPercentage": 0.25,
                    "threePointersMade": 1,
                    "threePointersAttempted": 4,
                    "threePointersPercentage": 0.25,
                    "freeThrowsMade": 0,
                    "freeThrowsAttempted": 0,
                    "freeThrowsPercentage": 0,
                    "reboundsOffensive": 0,
                    "reboundsDefensive": 0,
                    "reboundsTotal": 0,
                    "assists": 1,
                    "steals": 1,
                    "blocks": 0,
                    "turnovers": 0,
                    "foulsPersonal": 3,
                    "points": 3,
                    "plusMinusPoints": -11
                }
            },
            {
                "personId": 1630577,
                "firstName": "Julian",
                "familyName": "Champagnie",
                "nameI": "J. Champagnie",
                "playerSlug": "julian-champagnie",
                "position": "",
                "comment": "",
                "jerseyNum": "",
                "statistics": {
                    "minutes": "10:49",
                    "fieldGoalsMade": 1,
                    "fieldGoalsAttempted": 1,
                    "fieldGoalsPercentage": 1,
                    "threePointersMade": 1,
                    "threePointersAttempted": 1,
                    "threePointersPercentage": 1,
                    "freeThrowsMade": 0,
                    "freeThrowsAttempted": 0,
                    "freeThrowsPercentage": 0,
                    "reboundsOffensive": 0,
                    "reboundsDefensive": 1,
                    "reboundsTotal": 1,
                    "assists": 0,
                    "steals": 0,
                    "blocks": 1,
                    "turnovers": 1,
                    "foulsPersonal": 1,
                    "points": 3,
                    "plusMinusPoints": -7
                }
            },
            {
                "personId": 1631321,
                "firstName": "Sidy",
                "familyName": "Cissoko",
                "nameI": "S. Cissoko",
                "playerSlug": "sidy-cissoko",
                "position": "",
                "comment": "",
                "jerseyNum": "",
                "statistics": {
                    "minutes": "2:48",
                    "fieldGoalsMade": 0,
                    "fieldGoalsAttempted": 0,
                    "fieldGoalsPercentage": 0,
                    "threePointersMade": 0,
                    "threePointersAttempted": 0,
                    "threePointersPercentage": 0,
                    "freeThrowsMade": 0,
                    "freeThrowsAttempted": 0,
                    "freeThrowsPercentage": 0,
                    "reboundsOffensive": 0,
                    "reboundsDefensive": 0,
                    "reboundsTotal": 0,
                    "assists": 0,
                    "steals": 0,
                    "blocks": 0,
                    "turnovers": 0,
                    "foulsPersonal": 0,
                    "points": 0,
                    "plusMinusPoints": 1
                }
            },
            {
                "personId": 1631104,
                "firstName": "Blake",
                "familyName": "Wesley",
                "nameI": "B. Wesley",
                "playerSlug": "blake-wesley",
                "position": "",
                "comment": "",
                "jerseyNum": "",
                "statistics": {
                    "minutes": "2:48",
                    "fieldGoalsMade": 1,
                    "fieldGoalsAttempted": 1,
                    "fieldGoalsPercentage": 1,
                    "threePointersMade": 0,
                    "threePointersAttempted": 0,
                    "threePointersPercentage": 0,
                    "freeThrowsMade": 1,
                    "freeThrowsAttempted": 2,
                    "freeThrowsPercentage": 0.5,
                    "reboundsOffensive": 0,
                    "reboundsDefensive": 0,
                    "reboundsTotal": 0,
                    "assists": 2,
                    "steals": 0,
                    "blocks": 0,
                    "turnovers": 0,
                    "foulsPersonal": 0,
                    "points": 3,
                    "plusMinusPoints": 1
                }
            },
            {
                "personId": 1630572,
                "firstName": "Sandro",
                "familyName": "Mamukelashvili",
                "nameI": "S. Mamukelashvili",
                "playerSlug": "sandro-mamukelashvili",
                "position": "",
                "comment": "",
                "jerseyNum": "",
                "statistics": {
                    "minutes": "2:48",
                    "fieldGoalsMade": 0,
                    "fieldGoalsAttempted": 0,
                    "fieldGoalsPercentage": 0,
                    "threePointersMade": 0,
                    "threePointersAttempted": 0,
                    "threePointersPercentage": 0,
                    "freeThrowsMade": 0,
                    "freeThrowsAttempted": 0,
                    "freeThrowsPercentage": 0,
                    "reboundsOffensive": 0,
                    "reboundsDefensive": 1,
                    "reboundsTotal": 1,
                    "assists": 0,
                    "steals": 0,
                    "blocks": 0,
                    "turnovers": 0,
                    "foulsPersonal": 0,
                    "points": 0,
                    "plusMinusPoints": 1
                }
            },
            {
                "personId": 1628984,
                "firstName": "Devonte'",
                "familyName": "Graham",
                "nameI": "D. Graham",
                "playerSlug": "devonte-graham",
                "position": "",
                "comment": "DNP - Coach's Decision",
                "jerseyNum": "",
                "statistics": {
                    "minutes": "",
                    "fieldGoalsMade": 0,
                    "fieldGoalsAttempted": 0,
                    "fieldGoalsPercentage": 0,
                    "threePointersMade": 0,
                    "threePointersAttempted": 0,
                    "threePointersPercentage": 0,
                    "freeThrowsMade": 0,
                    "freeThrowsAttempted": 0,
                    "freeThrowsPercentage": 0,
                    "reboundsOffensive": 0,
                    "reboundsDefensive": 0,
                    "reboundsTotal": 0,
                    "assists": 0,
                    "steals": 0,
                    "blocks": 0,
                    "turnovers": 0,
                    "foulsPersonal": 0,
                    "points": 0,
                    "plusMinusPoints": 0
                }
            }
        ],
        "inactives": [
            {
                "personId": 1631230,
                "firstName": "Dominick",
                "familyName": "Barlow",
                "jerseyNum": "26  "
            },
            {
                "personId": 1641777,
                "firstName": "Charles",
                "familyName": "Bediako",
                "jerseyNum": "27  "
            },
            {
                "personId": 1629646,
                "firstName": "Charles",
                "familyName": "Bassey",
                "jerseyNum": "28  "
            },
            {
                "personId": 1630561,
                "firstName": "David",
                "familyName": "Duke Jr.",
                "jerseyNum": "88  "
            }
        ],
        "starters": {
            "minutes": "149:09",
            "fieldGoalsMade": 25,
            "fieldGoalsAttempted": 55,
            "fieldGoalsPercentage": 0.455,
            "threePointersMade": 5,
            "threePointersAttempted": 17,
            "threePointersPercentage": 0.294,
            "freeThrowsMade": 6,
            "freeThrowsAttempted": 10,
            "freeThrowsPercentage": 0.6,
            "reboundsOffensive": 6,
            "reboundsDefensive": 22,
            "reboundsTotal": 28,
            "assists": 13,
            "steals": 4,
            "blocks": 3,
            "turnovers": 10,
            "foulsPersonal": 4,
            "points": 61
        },
        "bench": {
            "minutes": "149:09",
            "fieldGoalsMade": 12,
            "fieldGoalsAttempted": 22,
            "fieldGoalsPercentage": 0.545,
            "threePointersMade": 5,
            "threePointersAttempted": 10,
            "threePointersPercentage": 0.5,
            "freeThrowsMade": 3,
            "freeThrowsAttempted": 4,
            "freeThrowsPercentage": 0.75,
            "reboundsOffensive": 3,
            "reboundsDefensive": 9,
            "reboundsTotal": 12,
            "assists": 8,
            "steals": 2,
            "blocks": 4,
            "turnovers": 7,
            "foulsPersonal": 6,
            "points": 32
        }
    },
    "lastFiveMeetings": {
        "meetings": [
            {
                "recencyOrder": 1,
                "gameId": "0022301223",
                "gameTimeUTC": "2023-12-09T01:30:00Z",
                "gameEt": "2023-12-08T20:30:00Z",
                "gameStatus": 3,
                "gameStatusText": "Final",
                "gameClock": "PT00M00.00S",
                "awayTeam": {
                    "teamId": 1610612741,
                    "teamCity": "Chicago",
                    "teamName": "Bulls",
                    "teamTricode": "CHI",
                    "teamSlug": "bulls",
                    "score": 121,
                    "wins": 9,
                    "losses": 14
                },
                "homeTeam": {
                    "teamId": 1610612759,
                    "teamCity": "San Antonio",
                    "teamName": "Spurs",
                    "teamTricode": "SAS",
                    "teamSlug": "spurs",
                    "score": 112,
                    "wins": 3,
                    "losses": 18
                }
            },
            {
                "recencyOrder": 2,
                "gameId": "0022200811",
                "gameTimeUTC": "2023-02-07T01:00:00Z",
                "gameEt": "2023-02-06T20:00:00Z",
                "gameStatus": 3,
                "gameStatusText": "Final",
                "gameClock": "PT00M00.00S",
                "awayTeam": {
                    "teamId": 1610612759,
                    "teamCity": "San Antonio",
                    "teamName": "Spurs",
                    "teamTricode": "SAS",
                    "teamSlug": "spurs",
                    "score": 104,
                    "wins": 14,
                    "losses": 40
                },
                "homeTeam": {
                    "teamId": 1610612741,
                    "teamCity": "Chicago",
                    "teamName": "Bulls",
                    "teamTricode": "CHI",
                    "teamSlug": "bulls",
                    "score": 128,
                    "wins": 26,
                    "losses": 27
                }
            },
            {
                "recencyOrder": 3,
                "gameId": "0022200077",
                "gameTimeUTC": "2022-10-29T00:30:00Z",
                "gameEt": "2022-10-28T20:30:00Z",
                "gameStatus": 3,
                "gameStatusText": "Final",
                "gameClock": "PT00M00.00S",
                "awayTeam": {
                    "teamId": 1610612741,
                    "teamCity": "Chicago",
                    "teamName": "Bulls",
                    "teamTricode": "CHI",
                    "teamSlug": "bulls",
                    "score": 124,
                    "wins": 3,
                    "losses": 3
                },
                "homeTeam": {
                    "teamId": 1610612759,
                    "teamCity": "San Antonio",
                    "teamName": "Spurs",
                    "teamTricode": "SAS",
                    "teamSlug": "spurs",
                    "score": 129,
                    "wins": 4,
                    "losses": 2
                }
            },
            {
                "recencyOrder": 4,
                "gameId": "0022100861",
                "gameTimeUTC": "2022-02-15T01:00:00Z",
                "gameEt": "2022-02-14T20:00:00Z",
                "gameStatus": 3,
                "gameStatusText": "Final",
                "gameClock": "PT00M00.00S",
                "awayTeam": {
                    "teamId": 1610612759,
                    "teamCity": "San Antonio",
                    "teamName": "Spurs",
                    "teamTricode": "SAS",
                    "teamSlug": "spurs",
                    "score": 109,
                    "wins": 22,
                    "losses": 36
                },
                "homeTeam": {
                    "teamId": 1610612741,
                    "teamCity": "Chicago",
                    "teamName": "Bulls",
                    "teamTricode": "CHI",
                    "teamSlug": "bulls",
                    "score": 120,
                    "wins": 37,
                    "losses": 21
                }
            },
            {
                "recencyOrder": 5,
                "gameId": "0022100742",
                "gameTimeUTC": "2022-01-29T01:30:00Z",
                "gameEt": "2022-01-28T20:30:00Z",
                "gameStatus": 3,
                "gameStatusText": "Final",
                "gameClock": "PT00M00.00S",
                "awayTeam": {
                    "teamId": 1610612741,
                    "teamCity": "Chicago",
                    "teamName": "Bulls",
                    "teamTricode": "CHI",
                    "teamSlug": "bulls",
                    "score": 122,
                    "wins": 30,
                    "losses": 18
                },
                "homeTeam": {
                    "teamId": 1610612759,
                    "teamCity": "San Antonio",
                    "teamName": "Spurs",
                    "teamTricode": "SAS",
                    "teamSlug": "spurs",
                    "score": 131,
                    "wins": 19,
                    "losses": 31
                }
            }
        ]
    },
    "pregameCharts": {
        "homeTeam": {
            "teamId": 1610612741,
            "teamCity": "Chicago",
            "teamName": "Bulls",
            "teamTricode": "CHI",
            "statistics": {
                "points": 112.3,
                "reboundsTotal": 43.8,
                "assists": 25,
                "steals": 7.8,
                "blocks": 4.8,
                "turnovers": 11.7,
                "fieldGoalsPercentage": 0.47,
                "threePointersPercentage": 0.358,
                "freeThrowsPercentage": 0.791,
                "pointsInThePaint": 48.4,
                "pointsSecondChance": 13.6,
                "pointsFastBreak": 12.5,
                "playerPtsLeaderFirstName": "DeMar",
                "playerPtsLeaderFamilyName": "DeRozan",
                "playerPtsLeaderId": 201942,
                "playerPtsLeaderPts": 24,
                "playerRebLeaderFirstName": "Nikola",
                "playerRebLeaderFamilyName": "Vucevic",
                "playerRebLeaderId": 202696,
                "playerRebLeaderReb": 10.5,
                "playerAstLeaderFirstName": "DeMar",
                "playerAstLeaderFamilyName": "DeRozan",
                "playerAstLeaderId": 201942,
                "playerAstLeaderAst": 5.3,
                "playerBlkLeaderFirstName": "Alex",
                "playerBlkLeaderFamilyName": "Caruso",
                "playerBlkLeaderId": 1627936,
                "playerBlkLeaderBlk": 0.99
            }
        },
        "awayTeam": {
            "teamId": 1610612759,
            "teamCity": "San Antonio",
            "teamName": "Spurs",
            "teamTricode": "SAS",
            "statistics": {
                "points": 112.1,
                "reboundsTotal": 44.2,
                "assists": 29.9,
                "steals": 7.1,
                "blocks": 6.3,
                "turnovers": 14.6,
                "fieldGoalsPercentage": 0.462,
                "threePointersPercentage": 0.347,
                "freeThrowsPercentage": 0.782,
                "pointsInThePaint": 51.4,
                "pointsSecondChance": 12.7,
                "pointsFastBreak": 15.6,
                "playerPtsLeaderFirstName": "Victor",
                "playerPtsLeaderFamilyName": "Wembanyama",
                "playerPtsLeaderId": 1641705,
                "playerPtsLeaderPts": 21.4,
                "playerRebLeaderFirstName": "Victor",
                "playerRebLeaderFamilyName": "Wembanyama",
                "playerRebLeaderId": 1641705,
                "playerRebLeaderReb": 10.6,
                "playerAstLeaderFirstName": "Tre",
                "playerAstLeaderFamilyName": "Jones",
                "playerAstLeaderId": 1630200,
                "playerAstLeaderAst": 6.2,
                "playerBlkLeaderFirstName": "Victor",
                "playerBlkLeaderFamilyName": "Wembanyama",
                "playerBlkLeaderId": 1641705,
                "playerBlkLeaderBlk": 3.58
            }
        }
    },
    "postgameCharts": {
        "homeTeam": {
            "teamId": 1610612741,
            "teamCity": "Chicago",
            "teamName": "Bulls",
            "teamTricode": "CHI",
            "statistics": {
                "points": 114,
                "reboundsTotal": 36,
                "assists": 24,
                "steals": 11,
                "blocks": 5,
                "turnovers": 11,
                "fieldGoalsPercentage": 0.544,
                "threePointersPercentage": 0.25,
                "freeThrowsPercentage": 0.818,
                "pointsInThePaint": 58,
                "pointsSecondChance": 8,
                "pointsFastBreak": 11,
                "biggestLead": 22,
                "leadChanges": 3,
                "timesTied": 5,
                "biggestScoringRun": 9,
                "turnoversTeam": 1,
                "turnoversTotal": 12,
                "reboundsTeam": 11,
                "pointsFromTurnovers": 20,
                "benchPoints": 29,
                "playerPtsLeaderFirstName": "Coby",
                "playerPtsLeaderFamilyName": "White",
                "playerPtsLeaderId": 1629632,
                "playerPtsLeaderPts": 22,
                "playerRebLeaderFirstName": "Andre",
                "playerRebLeaderFamilyName": "Drummond",
                "playerRebLeaderId": 203083,
                "playerRebLeaderReb": 8,
                "playerAstLeaderFirstName": "DeMar",
                "playerAstLeaderFamilyName": "DeRozan",
                "playerAstLeaderId": 201942,
                "playerAstLeaderAst": 5,
                "playerBlkLeaderFirstName": "Andre",
                "playerBlkLeaderFamilyName": "Drummond",
                "playerBlkLeaderId": 203083,
                "playerBlkLeaderBlk": 2
            }
        },
        "awayTeam": {
            "teamId": 1610612759,
            "teamCity": "San Antonio",
            "teamName": "Spurs",
            "teamTricode": "SAS",
            "statistics": {
                "points": 95,
                "reboundsTotal": 41,
                "assists": 24,
                "steals": 6,
                "blocks": 7,
                "turnovers": 19,
                "fieldGoalsPercentage": 0.457,
                "threePointersPercentage": 0.333,
                "freeThrowsPercentage": 0.688,
                "pointsInThePaint": 46,
                "pointsSecondChance": 8,
                "pointsFastBreak": 21,
                "biggestLead": 6,
                "leadChanges": 3,
                "timesTied": 5,
                "biggestScoringRun": 7,
                "turnoversTeam": 0,
                "turnoversTotal": 19,
                "reboundsTeam": 4,
                "pointsFromTurnovers": 8,
                "benchPoints": 34,
                "playerPtsLeaderFirstName": "Devin",
                "playerPtsLeaderFamilyName": "Vassell",
                "playerPtsLeaderId": 1630170,
                "playerPtsLeaderPts": 21,
                "playerRebLeaderFirstName": "Zach",
                "playerRebLeaderFamilyName": "Collins",
                "playerRebLeaderId": 1628380,
                "playerRebLeaderReb": 9,
                "playerAstLeaderFirstName": "Victor",
                "playerAstLeaderFamilyName": "Wembanyama",
                "playerAstLeaderId": 1641705,
                "playerAstLeaderAst": 5,
                "playerBlkLeaderFirstName": "Zach",
                "playerBlkLeaderFamilyName": "Collins",
                "playerBlkLeaderId": 1628380,
                "playerBlkLeaderBlk": 3
            }
        }
    },
    "videoAvailableFlag": 1,
    "ptAvailable": 1,
    "ptXYZAvailable": 0,
    "whStatus": 1,
    "hustleStatus": 1,
    "historicalStatus": 0,
    "gameSubtype": "",
    "branchUrl": "https://nba.smart.link/2g4lj7g0e?gameid=1242834",
    "ogImage": "https://cdn.nba.com/davinci/images/team-matchups/nba/latest/web/sas-chi/1200x628.png",
    "hideLineScores": false,
    "hideGameCharts": false,
    "homeTeamPlayers": [
        {
            "personId": 1627936,
            "name": "Alex Caruso",
            "nameI": "A. Caruso",
            "firstName": "Alex",
            "familyName": "Caruso",
            "jerseyNum": "6"
        },
        {
            "personId": 1629632,
            "name": "Coby White",
            "nameI": "C. White",
            "firstName": "Coby",
            "familyName": "White",
            "jerseyNum": "0"
        },
        {
            "personId": 1630678,
            "name": "Terry Taylor",
            "nameI": "T. Taylor",
            "firstName": "Terry",
            "familyName": "Taylor",
            "jerseyNum": "32"
        },
        {
            "personId": 1641763,
            "name": "Julian Phillips",
            "nameI": "J. Phillips",
            "firstName": "Julian",
            "familyName": "Phillips",
            "jerseyNum": "15"
        },
        {
            "personId": 1630245,
            "name": "Ayo Dosunmu",
            "nameI": "A. Dosunmu",
            "firstName": "Ayo",
            "familyName": "Dosunmu",
            "jerseyNum": "12"
        },
        {
            "personId": 1630172,
            "name": "Patrick Williams",
            "nameI": "P. Williams",
            "firstName": "Patrick",
            "familyName": "Williams",
            "jerseyNum": "44"
        },
        {
            "personId": 202696,
            "name": "Nikola Vucevic",
            "nameI": "N. Vucevic",
            "firstName": "Nikola",
            "familyName": "Vucevic",
            "jerseyNum": "9"
        },
        {
            "personId": 203083,
            "name": "Andre Drummond",
            "nameI": "A. Drummond",
            "firstName": "Andre",
            "familyName": "Drummond",
            "jerseyNum": "3"
        },
        {
            "personId": 201942,
            "name": "DeMar DeRozan",
            "nameI": "D. DeRozan",
            "firstName": "DeMar",
            "familyName": "DeRozan",
            "jerseyNum": "11"
        },
        {
            "personId": 1631207,
            "name": "Dalen Terry",
            "nameI": "D. Terry",
            "firstName": "Dalen",
            "familyName": "Terry",
            "jerseyNum": "25"
        },
        {
            "personId": 1628975,
            "name": "Jevon Carter",
            "nameI": "J. Carter",
            "firstName": "Jevon",
            "familyName": "Carter",
            "jerseyNum": "5"
        },
        {
            "personId": 1628470,
            "name": "Torrey Craig",
            "nameI": "T. Craig",
            "firstName": "Torrey",
            "familyName": "Craig",
            "jerseyNum": "13"
        }
    ],
    "awayTeamPlayers": [
        {
            "personId": 1631103,
            "name": "Malaki Branham",
            "nameI": "M. Branham",
            "firstName": "Malaki",
            "familyName": "Branham",
            "jerseyNum": "22"
        },
        {
            "personId": 1630577,
            "name": "Julian Champagnie",
            "nameI": "J. Champagnie",
            "firstName": "Julian",
            "familyName": "Champagnie",
            "jerseyNum": "30"
        },
        {
            "personId": 1629640,
            "name": "Keldon Johnson",
            "nameI": "K. Johnson",
            "firstName": "Keldon",
            "familyName": "Johnson",
            "jerseyNum": "3"
        },
        {
            "personId": 1630572,
            "name": "Sandro Mamukelashvili",
            "nameI": "S. Mamukelashvili",
            "firstName": "Sandro",
            "familyName": "Mamukelashvili",
            "jerseyNum": "54"
        },
        {
            "personId": 1628984,
            "name": "Devonte' Graham",
            "nameI": "D. Graham",
            "firstName": "Devonte'",
            "familyName": "Graham",
            "jerseyNum": "4"
        },
        {
            "personId": 203926,
            "name": "Doug McDermott",
            "nameI": "D. McDermott",
            "firstName": "Doug",
            "familyName": "McDermott",
            "jerseyNum": "17"
        },
        {
            "personId": 1628380,
            "name": "Zach Collins",
            "nameI": "Z. Collins",
            "firstName": "Zach",
            "familyName": "Collins",
            "jerseyNum": "23"
        },
        {
            "personId": 1631321,
            "name": "Sidy Cissoko",
            "nameI": "S. Cissoko",
            "firstName": "Sidy",
            "familyName": "Cissoko",
            "jerseyNum": "25"
        },
        {
            "personId": 1630200,
            "name": "Tre Jones",
            "nameI": "T. Jones",
            "firstName": "Tre",
            "familyName": "Jones",
            "jerseyNum": "33"
        },
        {
            "personId": 1631110,
            "name": "Jeremy Sochan",
            "nameI": "J. Sochan",
            "firstName": "Jeremy",
            "familyName": "Sochan",
            "jerseyNum": "10"
        },
        {
            "personId": 1626224,
            "name": "Cedi Osman",
            "nameI": "C. Osman",
            "firstName": "Cedi",
            "familyName": "Osman",
            "jerseyNum": "16"
        },
        {
            "personId": 1630170,
            "name": "Devin Vassell",
            "nameI": "D. Vassell",
            "firstName": "Devin",
            "familyName": "Vassell",
            "jerseyNum": "24"
        },
        {
            "personId": 1631104,
            "name": "Blake Wesley",
            "nameI": "B. Wesley",
            "firstName": "Blake",
            "familyName": "Wesley",
            "jerseyNum": "14"
        },
        {
            "personId": 1641705,
            "name": "Victor Wembanyama",
            "nameI": "V. Wembanyama",
            "firstName": "Victor",
            "familyName": "Wembanyama",
            "jerseyNum": "1"
        }
    ],
    "hyperlinks": [],
    "pbOdds": {},
    "gameRecap": {
        "id": 1248351,
        "gameId": "0022300376",
        "title": "Game Recap: Bulls 114, Spurs 95",
        "permalink": "https://www.nba.com/watch/video/game-recap-bulls-114-spurs-95",
        "slug": "game-recap-bulls-114-spurs-95",
        "entitlements": "free",
        "videoDuration": "02:13",
        "excerpt": "The Bulls defeated the Spurs, 114-95. Coby White led the Bulls with 22 points (10-15 FG), six rebounds, and five assists as DeMar DeRozan totaled 21 points, four rebounds, and five assists. Devin Vassell led San Antonio with 21 points while Zach Collins added 14 points, nine rebounds, and three blocks. The Bulls have won three in a row and improve to 13-17 as the Spurs move to 4-23. ",
        "featuredImage": "https://cdn.nba.com/manage/2023/12/Full-Game-Highlights-Recap-YT-Thumbnail-23-24-SAS-CHI-Recap.jpg"
    }
}