{
    "gameId": "0022301060",
    "gameCode": "20240328/BOSATL",
    "gameStatus": 3,
    "gameStatusText": "Final/OT",
    "period": 5,
    "gameClock": "PT00M00.00S",
    "gameTimeUTC": "2024-03-28T23:30:00Z",
    "gameEt": "2024-03-28T19:30:00Z",
    "awayTeamId": 1610612738,
    "homeTeamId": 1610612737,
    "duration": "2:24",
    "attendance": 17743,
    "sellout": 1,
    "seriesGameNumber": "",
    "gameLabel": "",
    "gameSubLabel": "",
    "seriesText": "",
    "ifNecessary": false,
    "arena": {
        "arenaId": 650,
        "arenaName": "State Farm Arena",
        "arenaCity": "Atlanta",
        "arenaState": "GA",
        "arenaCountry": "US",
        "arenaTimezone": "Eastern",
        "arenaStreetAddress": "",
        "arenaPostalCode": ""
    },
    "officials": [
        {
            "personId": 2530,
            "name": "Ed Malloy",
            "nameI": "E. Malloy",
            "firstName": "Ed",
            "familyName": "Malloy",
            "jerseyNum": "14  ",
            "assignment": ""
        },
        {
            "personId": 1626300,
            "name": "Ray Acosta",
            "nameI": "R. Acosta",
            "firstName": "Ray",
            "familyName": "Acosta",
            "jerseyNum": "54  ",
            "assignment": ""
        },
        {
            "personId": 1628484,
            "name": "Dannica Mosher",
            "nameI": "D. Mosher",
            "firstName": "Dannica",
            "familyName": "Mosher",
            "jerseyNum": "89  ",
            "assignment": ""
        }
    ],
    "broadcasters": {
        "nationalBroadcasters": [],
        "nationalRadioBroadcasters": [
            {
                "broadcasterId": 1001098,
                "broadcastDisplay": "SiriusXM",
                "broadcasterDisplay": "SiriusXM",
                "broadcasterVideoLink": "https://sxm.app.link/NBAWaysWatch",
                "broadcasterDescription": null,
                "broadcasterTeamId": -1
            }
        ],
        "nationalOttBroadcasters": [],
        "homeTvBroadcasters": [
            {
                "broadcasterId": 1000356,
                "broadcastDisplay": "BSSE-ATL",
                "broadcasterDisplay": "Bally Sports SE-ATL",
                "broadcasterVideoLink": "",
                "broadcasterDescription": null,
                "broadcasterTeamId": 1610612737
            }
        ],
        "homeRadioBroadcasters": [
            {
                "broadcasterId": 1491,
                "broadcastDisplay": "WZGC",
                "broadcasterDisplay": "WZGC",
                "broadcasterVideoLink": "",
                "broadcasterDescription": null,
                "broadcasterTeamId": 1610612737
            }
        ],
        "homeOttBroadcasters": [],
        "awayTvBroadcasters": [
            {
                "broadcasterId": 1658,
                "broadcastDisplay": "NBCSB",
                "broadcasterDisplay": "NBC Sports Boston",
                "broadcasterVideoLink": "http://stream.nbcsports.com/rsn/nba-celtics-live-stream",
                "broadcasterDescription": null,
                "broadcasterTeamId": 1610612738
            }
        ],
        "awayRadioBroadcasters": [
            {
                "broadcasterId": 1471,
                "broadcastDisplay": "WBZ-FM",
                "broadcasterDisplay": "98.5 The Sports Hub",
                "broadcasterVideoLink": "",
                "broadcasterDescription": null,
                "broadcasterTeamId": 1610612738
            }
        ],
        "awayOttBroadcasters": []
    },
    "homeTeam": {
        "teamId": 1610612737,
        "teamName": "Hawks",
        "teamCity": "Atlanta",
        "teamTricode": "ATL",
        "teamSlug": "hawks",
        "teamWins": 34,
        "teamLosses": 39,
        "score": 123,
        "inBonus": "",
        "timeoutsRemaining": 0,
        "seed": 0,
        "statistics": {
            "minutes": "265:00",
            "fieldGoalsMade": 51,
            "fieldGoalsAttempted": 104,
            "fieldGoalsPercentage": 0.49,
            "threePointersMade": 15,
            "threePointersAttempted": 44,
            "threePointersPercentage": 0.341,
            "freeThrowsMade": 6,
            "freeThrowsAttempted": 10,
            "freeThrowsPercentage": 0.6,
            "reboundsOffensive": 17,
            "reboundsDefensive": 36,
            "reboundsTotal": 53,
            "assists": 24,
            "steals": 5,
            "blocks": 5,
            "turnovers": 11,
            "foulsPersonal": 17,
            "points": 123,
            "plusMinusPoints": 1
        },
        "periods": [
            {
                "period": 1,
                "periodType": "REGULAR",
                "score": 28
            },
            {
                "period": 2,
                "periodType": "REGULAR",
                "score": 31
            },
            {
                "period": 3,
                "periodType": "REGULAR",
                "score": 30
            },
            {
                "period": 4,
                "periodType": "REGULAR",
                "score": 23
            },
            {
                "period": 5,
                "periodType": "OVERTIME",
                "score": 11
            }
        ],
        "players": [
            {
                "personId": 1630249,
                "firstName": "V\u00edt",
                "familyName": "Krej\u010d\u00ed",
                "nameI": "V. Krej\u010d\u00ed",
                "playerSlug": "v\u00edt-krej\u010d\u00ed",
                "position": "F",
                "comment": "",
                "jerseyNum": "",
                "statistics": {
                    "minutes": "35:12",
                    "fieldGoalsMade": 1,
                    "fieldGoalsAttempted": 1,
                    "fieldGoalsPercentage": 1,
                    "threePointersMade": 0,
                    "threePointersAttempted": 0,
                    "threePointersPercentage": 0,
                    "freeThrowsMade": 0,
                    "freeThrowsAttempted": 0,
                    "freeThrowsPercentage": 0,
                    "reboundsOffensive": 1,
                    "reboundsDefensive": 2,
                    "reboundsTotal": 3,
                    "assists": 1,
                    "steals": 0,
                    "blocks": 0,
                    "turnovers": 0,
                    "foulsPersonal": 6,
                    "points": 2,
                    "plusMinusPoints": 0
                }
            },
            {
                "personId": 1629631,
                "firstName": "De'Andre",
                "familyName": "Hunter",
                "nameI": "D. Hunter",
                "playerSlug": "deandre-hunter",
                "position": "F",
                "comment": "",
                "jerseyNum": "",
                "statistics": {
                    "minutes": "39:51",
                    "fieldGoalsMade": 8,
                    "fieldGoalsAttempted": 16,
                    "fieldGoalsPercentage": 0.5,
                    "threePointersMade": 5,
                    "threePointersAttempted": 9,
                    "threePointersPercentage": 0.556,
                    "freeThrowsMade": 0,
                    "freeThrowsAttempted": 3,
                    "freeThrowsPercentage": 0,
                    "reboundsOffensive": 2,
                    "reboundsDefensive": 11,
                    "reboundsTotal": 13,
                    "assists": 1,
                    "steals": 0,
                    "blocks": 0,
                    "turnovers": 1,
                    "foulsPersonal": 0,
                    "points": 21,
                    "plusMinusPoints": 1
                }
            },
            {
                "personId": 203991,
                "firstName": "Clint",
                "familyName": "Capela",
                "nameI": "C. Capela",
                "playerSlug": "clint-capela",
                "position": "C",
                "comment": "",
                "jerseyNum": "",
                "statistics": {
                    "minutes": "33:17",
                    "fieldGoalsMade": 6,
                    "fieldGoalsAttempted": 8,
                    "fieldGoalsPercentage": 0.75,
                    "threePointersMade": 0,
                    "threePointersAttempted": 0,
                    "threePointersPercentage": 0,
                    "freeThrowsMade": 0,
                    "freeThrowsAttempted": 0,
                    "freeThrowsPercentage": 0,
                    "reboundsOffensive": 7,
                    "reboundsDefensive": 6,
                    "reboundsTotal": 13,
                    "assists": 3,
                    "steals": 0,
                    "blocks": 2,
                    "turnovers": 2,
                    "foulsPersonal": 2,
                    "points": 12,
                    "plusMinusPoints": 0
                }
            },
            {
                "personId": 203992,
                "firstName": "Bogdan",
                "familyName": "Bogdanovi\u0107",
                "nameI": "B. Bogdanovi\u0107",
                "playerSlug": "bogdan-bogdanovi\u0107",
                "position": "G",
                "comment": "",
                "jerseyNum": "",
                "statistics": {
                    "minutes": "43:27",
                    "fieldGoalsMade": 9,
                    "fieldGoalsAttempted": 19,
                    "fieldGoalsPercentage": 0.474,
                    "threePointersMade": 2,
                    "threePointersAttempted": 8,
                    "threePointersPercentage": 0.25,
                    "freeThrowsMade": 4,
                    "freeThrowsAttempted": 4,
                    "freeThrowsPercentage": 1,
                    "reboundsOffensive": 3,
                    "reboundsDefensive": 4,
                    "reboundsTotal": 7,
                    "assists": 5,
                    "steals": 1,
                    "blocks": 0,
                    "turnovers": 2,
                    "foulsPersonal": 1,
                    "points": 24,
                    "plusMinusPoints": 3
                }
            },
            {
                "personId": 1627749,
                "firstName": "Dejounte",
                "familyName": "Murray",
                "nameI": "D. Murray",
                "playerSlug": "dejounte-murray",
                "position": "G",
                "comment": "",
                "jerseyNum": "",
                "statistics": {
                    "minutes": "46:48",
                    "fieldGoalsMade": 18,
                    "fieldGoalsAttempted": 44,
                    "fieldGoalsPercentage": 0.409,
                    "threePointersMade": 6,
                    "threePointersAttempted": 19,
                    "threePointersPercentage": 0.316,
                    "freeThrowsMade": 2,
                    "freeThrowsAttempted": 2,
                    "freeThrowsPercentage": 1,
                    "reboundsOffensive": 0,
                    "reboundsDefensive": 7,
                    "reboundsTotal": 7,
                    "assists": 7,
                    "steals": 2,
                    "blocks": 1,
                    "turnovers": 3,
                    "foulsPersonal": 2,
                    "points": 44,
                    "plusMinusPoints": 3
                }
            },
            {
                "personId": 1629726,
                "firstName": "Garrison",
                "familyName": "Mathews",
                "nameI": "G. Mathews",
                "playerSlug": "garrison-mathews",
                "position": "",
                "comment": "",
                "jerseyNum": "",
                "statistics": {
                    "minutes": "16:50",
                    "fieldGoalsMade": 3,
                    "fieldGoalsAttempted": 5,
                    "fieldGoalsPercentage": 0.6,
                    "threePointersMade": 1,
                    "threePointersAttempted": 3,
                    "threePointersPercentage": 0.333,
                    "freeThrowsMade": 0,
                    "freeThrowsAttempted": 0,
                    "freeThrowsPercentage": 0,
                    "reboundsOffensive": 0,
                    "reboundsDefensive": 1,
                    "reboundsTotal": 1,
                    "assists": 1,
                    "steals": 0,
                    "blocks": 0,
                    "turnovers": 1,
                    "foulsPersonal": 0,
                    "points": 7,
                    "plusMinusPoints": 0
                }
            },
            {
                "personId": 1628981,
                "firstName": "Bruno",
                "familyName": "Fernando",
                "nameI": "B. Fernando",
                "playerSlug": "bruno-fernando",
                "position": "",
                "comment": "",
                "jerseyNum": "",
                "statistics": {
                    "minutes": "19:43",
                    "fieldGoalsMade": 3,
                    "fieldGoalsAttempted": 3,
                    "fieldGoalsPercentage": 1,
                    "threePointersMade": 0,
                    "threePointersAttempted": 0,
                    "threePointersPercentage": 0,
                    "freeThrowsMade": 0,
                    "freeThrowsAttempted": 1,
                    "freeThrowsPercentage": 0,
                    "reboundsOffensive": 1,
                    "reboundsDefensive": 3,
                    "reboundsTotal": 4,
                    "assists": 2,
                    "steals": 1,
                    "blocks": 1,
                    "turnovers": 0,
                    "foulsPersonal": 3,
                    "points": 6,
                    "plusMinusPoints": 1
                }
            },
            {
                "personId": 202083,
                "firstName": "Wesley",
                "familyName": "Matthews",
                "nameI": "W. Matthews",
                "playerSlug": "wesley-matthews",
                "position": "",
                "comment": "",
                "jerseyNum": "",
                "statistics": {
                    "minutes": "23:40",
                    "fieldGoalsMade": 1,
                    "fieldGoalsAttempted": 6,
                    "fieldGoalsPercentage": 0.167,
                    "threePointersMade": 1,
                    "threePointersAttempted": 5,
                    "threePointersPercentage": 0.2,
                    "freeThrowsMade": 0,
                    "freeThrowsAttempted": 0,
                    "freeThrowsPercentage": 0,
                    "reboundsOffensive": 3,
                    "reboundsDefensive": 2,
                    "reboundsTotal": 5,
                    "assists": 3,
                    "steals": 1,
                    "blocks": 1,
                    "turnovers": 1,
                    "foulsPersonal": 3,
                    "points": 3,
                    "plusMinusPoints": -1
                }
            },
            {
                "personId": 1630235,
                "firstName": "Trent",
                "familyName": "Forrest",
                "nameI": "T. Forrest",
                "playerSlug": "trent-forrest",
                "position": "",
                "comment": "",
                "jerseyNum": "",
                "statistics": {
                    "minutes": "6:12",
                    "fieldGoalsMade": 2,
                    "fieldGoalsAttempted": 2,
                    "fieldGoalsPercentage": 1,
                    "threePointersMade": 0,
                    "threePointersAttempted": 0,
                    "threePointersPercentage": 0,
                    "freeThrowsMade": 0,
                    "freeThrowsAttempted": 0,
                    "freeThrowsPercentage": 0,
                    "reboundsOffensive": 0,
                    "reboundsDefensive": 0,
                    "reboundsTotal": 0,
                    "assists": 1,
                    "steals": 0,
                    "blocks": 0,
                    "turnovers": 1,
                    "foulsPersonal": 0,
                    "points": 4,
                    "plusMinusPoints": -2
                }
            },
            {
                "personId": 1630552,
                "firstName": "Jalen",
                "familyName": "Johnson",
                "nameI": "J. Johnson",
                "playerSlug": "jalen-johnson",
                "position": "",
                "comment": "DND - Injury/Illness",
                "jerseyNum": "",
                "statistics": {
                    "minutes": "",
                    "fieldGoalsMade": 0,
                    "fieldGoalsAttempted": 0,
                    "fieldGoalsPercentage": 0,
                    "threePointersMade": 0,
                    "threePointersAttempted": 0,
                    "threePointersPercentage": 0,
                    "freeThrowsMade": 0,
                    "freeThrowsAttempted": 0,
                    "freeThrowsPercentage": 0,
                    "reboundsOffensive": 0,
                    "reboundsDefensive": 0,
                    "reboundsTotal": 0,
                    "assists": 0,
                    "steals": 0,
                    "blocks": 0,
                    "turnovers": 0,
                    "foulsPersonal": 0,
                    "points": 0,
                    "plusMinusPoints": 0
                }
            },
            {
                "personId": 1629685,
                "firstName": "Dylan",
                "familyName": "Windler",
                "nameI": "D. Windler",
                "playerSlug": "dylan-windler",
                "position": "",
                "comment": "DNP - Coach's Decision",
                "jerseyNum": "",
                "statistics": {
                    "minutes": "",
                    "fieldGoalsMade": 0,
                    "fieldGoalsAttempted": 0,
                    "fieldGoalsPercentage": 0,
                    "threePointersMade": 0,
                    "threePointersAttempted": 0,
                    "threePointersPercentage": 0,
                    "freeThrowsMade": 0,
                    "freeThrowsAttempted": 0,
                    "freeThrowsPercentage": 0,
                    "reboundsOffensive": 0,
                    "reboundsDefensive": 0,
                    "reboundsTotal": 0,
                    "assists": 0,
                    "steals": 0,
                    "blocks": 0,
                    "turnovers": 0,
                    "foulsPersonal": 0,
                    "points": 0,
                    "plusMinusPoints": 0
                }
            },
            {
                "personId": 1629027,
                "firstName": "Trae",
                "familyName": "Young",
                "nameI": "T. Young",
                "playerSlug": "trae-young",
                "position": "",
                "comment": "DND - Injury/Illness",
                "jerseyNum": "",
                "statistics": {
                    "minutes": "",
                    "fieldGoalsMade": 0,
                    "fieldGoalsAttempted": 0,
                    "fieldGoalsPercentage": 0,
                    "threePointersMade": 0,
                    "threePointersAttempted": 0,
                    "threePointersPercentage": 0,
                    "freeThrowsMade": 0,
                    "freeThrowsAttempted": 0,
                    "freeThrowsPercentage": 0,
                    "reboundsOffensive": 0,
                    "reboundsDefensive": 0,
                    "reboundsTotal": 0,
                    "assists": 0,
                    "steals": 0,
                    "blocks": 0,
                    "turnovers": 0,
                    "foulsPersonal": 0,
                    "points": 0,
                    "plusMinusPoints": 0
                }
            }
        ],
        "inactives": [
            {
                "personId": 1641754,
                "firstName": "Seth",
                "familyName": "Lundy",
                "jerseyNum": "3   "
            },
            {
                "personId": 1630180,
                "firstName": "Saddiq",
                "familyName": "Bey",
                "jerseyNum": "41  "
            },
            {
                "personId": 1631243,
                "firstName": "Mouhamed",
                "familyName": "Gueye",
                "jerseyNum": "18  "
            },
            {
                "personId": 1630168,
                "firstName": "Onyeka",
                "familyName": "Okongwu",
                "jerseyNum": "17  "
            },
            {
                "personId": 1631100,
                "firstName": "AJ",
                "familyName": "Griffin",
                "jerseyNum": "14  "
            },
            {
                "personId": 1641723,
                "firstName": "Kobe",
                "familyName": "Bufkin",
                "jerseyNum": "4   "
            }
        ],
        "starters": {
            "minutes": "198:35",
            "fieldGoalsMade": 42,
            "fieldGoalsAttempted": 88,
            "fieldGoalsPercentage": 0.477,
            "threePointersMade": 13,
            "threePointersAttempted": 36,
            "threePointersPercentage": 0.361,
            "freeThrowsMade": 6,
            "freeThrowsAttempted": 9,
            "freeThrowsPercentage": 0.667,
            "reboundsOffensive": 13,
            "reboundsDefensive": 30,
            "reboundsTotal": 43,
            "assists": 17,
            "steals": 3,
            "blocks": 3,
            "turnovers": 8,
            "foulsPersonal": 11,
            "points": 103
        },
        "bench": {
            "minutes": "198:35",
            "fieldGoalsMade": 9,
            "fieldGoalsAttempted": 16,
            "fieldGoalsPercentage": 0.563,
            "threePointersMade": 2,
            "threePointersAttempted": 8,
            "threePointersPercentage": 0.25,
            "freeThrowsMade": 0,
            "freeThrowsAttempted": 1,
            "freeThrowsPercentage": 0,
            "reboundsOffensive": 4,
            "reboundsDefensive": 6,
            "reboundsTotal": 10,
            "assists": 7,
            "steals": 2,
            "blocks": 2,
            "turnovers": 3,
            "foulsPersonal": 6,
            "points": 20
        }
    },
    "awayTeam": {
        "teamId": 1610612738,
        "teamName": "Celtics",
        "teamCity": "Boston",
        "teamTricode": "BOS",
        "teamSlug": "celtics",
        "teamWins": 57,
        "teamLosses": 16,
        "score": 122,
        "inBonus": "",
        "timeoutsRemaining": 0,
        "seed": 0,
        "statistics": {
            "minutes": "265:00",
            "fieldGoalsMade": 45,
            "fieldGoalsAttempted": 94,
            "fieldGoalsPercentage": 0.479,
            "threePointersMade": 14,
            "threePointersAttempted": 36,
            "threePointersPercentage": 0.389,
            "freeThrowsMade": 18,
            "freeThrowsAttempted": 21,
            "freeThrowsPercentage": 0.857,
            "reboundsOffensive": 9,
            "reboundsDefensive": 34,
            "reboundsTotal": 43,
            "assists": 28,
            "steals": 7,
            "blocks": 6,
            "turnovers": 12,
            "foulsPersonal": 15,
            "points": 122,
            "plusMinusPoints": -1
        },
        "periods": [
            {
                "period": 1,
                "periodType": "REGULAR",
                "score": 29
            },
            {
                "period": 2,
                "periodType": "REGULAR",
                "score": 34
            },
            {
                "period": 3,
                "periodType": "REGULAR",
                "score": 27
            },
            {
                "period": 4,
                "periodType": "REGULAR",
                "score": 22
            },
            {
                "period": 5,
                "periodType": "OVERTIME",
                "score": 10
            }
        ],
        "players": [
            {
                "personId": 1627759,
                "firstName": "Jaylen",
                "familyName": "Brown",
                "nameI": "J. Brown",
                "playerSlug": "jaylen-brown",
                "position": "F",
                "comment": "",
                "jerseyNum": "",
                "statistics": {
                    "minutes": "38:49",
                    "fieldGoalsMade": 9,
                    "fieldGoalsAttempted": 17,
                    "fieldGoalsPercentage": 0.529,
                    "threePointersMade": 0,
                    "threePointersAttempted": 3,
                    "threePointersPercentage": 0,
                    "freeThrowsMade": 0,
                    "freeThrowsAttempted": 0,
                    "freeThrowsPercentage": 0,
                    "reboundsOffensive": 0,
                    "reboundsDefensive": 1,
                    "reboundsTotal": 1,
                    "assists": 4,
                    "steals": 2,
                    "blocks": 2,
                    "turnovers": 3,
                    "foulsPersonal": 3,
                    "points": 18,
                    "plusMinusPoints": 8
                }
            },
            {
                "personId": 1628369,
                "firstName": "Jayson",
                "familyName": "Tatum",
                "nameI": "J. Tatum",
                "playerSlug": "jayson-tatum",
                "position": "F",
                "comment": "",
                "jerseyNum": "",
                "statistics": {
                    "minutes": "45:14",
                    "fieldGoalsMade": 9,
                    "fieldGoalsAttempted": 22,
                    "fieldGoalsPercentage": 0.409,
                    "threePointersMade": 2,
                    "threePointersAttempted": 7,
                    "threePointersPercentage": 0.286,
                    "freeThrowsMade": 11,
                    "freeThrowsAttempted": 13,
                    "freeThrowsPercentage": 0.846,
                    "reboundsOffensive": 3,
                    "reboundsDefensive": 10,
                    "reboundsTotal": 13,
                    "assists": 6,
                    "steals": 0,
                    "blocks": 0,
                    "turnovers": 2,
                    "foulsPersonal": 3,
                    "points": 31,
                    "plusMinusPoints": -11
                }
            },
            {
                "personId": 204001,
                "firstName": "Kristaps",
                "familyName": "Porzi\u0146\u0123is",
                "nameI": "K. Porzi\u0146\u0123is",
                "playerSlug": "kristaps-porzi\u0146\u0123is",
                "position": "C",
                "comment": "",
                "jerseyNum": "",
                "statistics": {
                    "minutes": "40:36",
                    "fieldGoalsMade": 8,
                    "fieldGoalsAttempted": 20,
                    "fieldGoalsPercentage": 0.4,
                    "threePointersMade": 2,
                    "threePointersAttempted": 7,
                    "threePointersPercentage": 0.286,
                    "freeThrowsMade": 2,
                    "freeThrowsAttempted": 3,
                    "freeThrowsPercentage": 0.667,
                    "reboundsOffensive": 2,
                    "reboundsDefensive": 5,
                    "reboundsTotal": 7,
                    "assists": 2,
                    "steals": 1,
                    "blocks": 3,
                    "turnovers": 3,
                    "foulsPersonal": 3,
                    "points": 20,
                    "plusMinusPoints": -4
                }
            },
            {
                "personId": 201950,
                "firstName": "Jrue",
                "familyName": "Holiday",
                "nameI": "J. Holiday",
                "playerSlug": "jrue-holiday",
                "position": "G",
                "comment": "",
                "jerseyNum": "",
                "statistics": {
                    "minutes": "36:32",
                    "fieldGoalsMade": 5,
                    "fieldGoalsAttempted": 11,
                    "fieldGoalsPercentage": 0.455,
                    "threePointersMade": 3,
                    "threePointersAttempted": 6,
                    "threePointersPercentage": 0.5,
                    "freeThrowsMade": 0,
                    "freeThrowsAttempted": 0,
                    "freeThrowsPercentage": 0,
                    "reboundsOffensive": 1,
                    "reboundsDefensive": 6,
                    "reboundsTotal": 7,
                    "assists": 5,
                    "steals": 1,
                    "blocks": 1,
                    "turnovers": 0,
                    "foulsPersonal": 1,
                    "points": 13,
                    "plusMinusPoints": -1
                }
            },
            {
                "personId": 1628401,
                "firstName": "Derrick",
                "familyName": "White",
                "nameI": "D. White",
                "playerSlug": "derrick-white",
                "position": "G",
                "comment": "",
                "jerseyNum": "",
                "statistics": {
                    "minutes": "41:00",
                    "fieldGoalsMade": 8,
                    "fieldGoalsAttempted": 11,
                    "fieldGoalsPercentage": 0.727,
                    "threePointersMade": 5,
                    "threePointersAttempted": 6,
                    "threePointersPercentage": 0.833,
                    "freeThrowsMade": 1,
                    "freeThrowsAttempted": 1,
                    "freeThrowsPercentage": 1,
                    "reboundsOffensive": 2,
                    "reboundsDefensive": 5,
                    "reboundsTotal": 7,
                    "assists": 5,
                    "steals": 1,
                    "blocks": 0,
                    "turnovers": 3,
                    "foulsPersonal": 3,
                    "points": 22,
                    "plusMinusPoints": 3
                }
            },
            {
                "personId": 1630573,
                "firstName": "Sam",
                "familyName": "Hauser",
                "nameI": "S. Hauser",
                "playerSlug": "sam-hauser",
                "position": "",
                "comment": "",
                "jerseyNum": "",
                "statistics": {
                    "minutes": "22:31",
                    "fieldGoalsMade": 3,
                    "fieldGoalsAttempted": 6,
                    "fieldGoalsPercentage": 0.5,
                    "threePointersMade": 2,
                    "threePointersAttempted": 4,
                    "threePointersPercentage": 0.5,
                    "freeThrowsMade": 0,
                    "freeThrowsAttempted": 0,
                    "freeThrowsPercentage": 0,
                    "reboundsOffensive": 0,
                    "reboundsDefensive": 2,
                    "reboundsTotal": 2,
                    "assists": 3,
                    "steals": 0,
                    "blocks": 0,
                    "turnovers": 0,
                    "foulsPersonal": 1,
                    "points": 8,
                    "plusMinusPoints": 3
                }
            },
            {
                "personId": 1630214,
                "firstName": "Xavier",
                "familyName": "Tillman",
                "nameI": "X. Tillman",
                "playerSlug": "xavier-tillman",
                "position": "",
                "comment": "",
                "jerseyNum": "",
                "statistics": {
                    "minutes": "8:32",
                    "fieldGoalsMade": 1,
                    "fieldGoalsAttempted": 3,
                    "fieldGoalsPercentage": 0.333,
                    "threePointersMade": 0,
                    "threePointersAttempted": 2,
                    "threePointersPercentage": 0,
                    "freeThrowsMade": 0,
                    "freeThrowsAttempted": 0,
                    "freeThrowsPercentage": 0,
                    "reboundsOffensive": 0,
                    "reboundsDefensive": 2,
                    "reboundsTotal": 2,
                    "assists": 1,
                    "steals": 0,
                    "blocks": 0,
                    "turnovers": 0,
                    "foulsPersonal": 0,
                    "points": 2,
                    "plusMinusPoints": 5
                }
            },
            {
                "personId": 1630202,
                "firstName": "Payton",
                "familyName": "Pritchard",
                "nameI": "P. Pritchard",
                "playerSlug": "payton-pritchard",
                "position": "",
                "comment": "",
                "jerseyNum": "",
                "statistics": {
                    "minutes": "18:44",
                    "fieldGoalsMade": 1,
                    "fieldGoalsAttempted": 3,
                    "fieldGoalsPercentage": 0.333,
                    "threePointersMade": 0,
                    "threePointersAttempted": 1,
                    "threePointersPercentage": 0,
                    "freeThrowsMade": 2,
                    "freeThrowsAttempted": 2,
                    "freeThrowsPercentage": 1,
                    "reboundsOffensive": 0,
                    "reboundsDefensive": 1,
                    "reboundsTotal": 1,
                    "assists": 2,
                    "steals": 1,
                    "blocks": 0,
                    "turnovers": 1,
                    "foulsPersonal": 1,
                    "points": 4,
                    "plusMinusPoints": -11
                }
            },
            {
                "personId": 1628436,
                "firstName": "Luke",
                "familyName": "Kornet",
                "nameI": "L. Kornet",
                "playerSlug": "luke-kornet",
                "position": "",
                "comment": "",
                "jerseyNum": "",
                "statistics": {
                    "minutes": "13:02",
                    "fieldGoalsMade": 1,
                    "fieldGoalsAttempted": 1,
                    "fieldGoalsPercentage": 1,
                    "threePointersMade": 0,
                    "threePointersAttempted": 0,
                    "threePointersPercentage": 0,
                    "freeThrowsMade": 2,
                    "freeThrowsAttempted": 2,
                    "freeThrowsPercentage": 1,
                    "reboundsOffensive": 1,
                    "reboundsDefensive": 2,
                    "reboundsTotal": 3,
                    "assists": 0,
                    "steals": 1,
                    "blocks": 0,
                    "turnovers": 0,
                    "foulsPersonal": 0,
                    "points": 4,
                    "plusMinusPoints": 3
                }
            },
            {
                "personId": 1629052,
                "firstName": "Oshae",
                "familyName": "Brissett",
                "nameI": "O. Brissett",
                "playerSlug": "oshae-brissett",
                "position": "",
                "comment": "DNP - Coach's Decision",
                "jerseyNum": "",
                "statistics": {
                    "minutes": "",
                    "fieldGoalsMade": 0,
                    "fieldGoalsAttempted": 0,
                    "fieldGoalsPercentage": 0,
                    "threePointersMade": 0,
                    "threePointersAttempted": 0,
                    "threePointersPercentage": 0,
                    "freeThrowsMade": 0,
                    "freeThrowsAttempted": 0,
                    "freeThrowsPercentage": 0,
                    "reboundsOffensive": 0,
                    "reboundsDefensive": 0,
                    "reboundsTotal": 0,
                    "assists": 0,
                    "steals": 0,
                    "blocks": 0,
                    "turnovers": 0,
                    "foulsPersonal": 0,
                    "points": 0,
                    "plusMinusPoints": 0
                }
            },
            {
                "personId": 201143,
                "firstName": "Al",
                "familyName": "Horford",
                "nameI": "A. Horford",
                "playerSlug": "al-horford",
                "position": "",
                "comment": "DND - Injury/Illness",
                "jerseyNum": "",
                "statistics": {
                    "minutes": "",
                    "fieldGoalsMade": 0,
                    "fieldGoalsAttempted": 0,
                    "fieldGoalsPercentage": 0,
                    "threePointersMade": 0,
                    "threePointersAttempted": 0,
                    "threePointersPercentage": 0,
                    "freeThrowsMade": 0,
                    "freeThrowsAttempted": 0,
                    "freeThrowsPercentage": 0,
                    "reboundsOffensive": 0,
                    "reboundsDefensive": 0,
                    "reboundsTotal": 0,
                    "assists": 0,
                    "steals": 0,
                    "blocks": 0,
                    "turnovers": 0,
                    "foulsPersonal": 0,
                    "points": 0,
                    "plusMinusPoints": 0
                }
            },
            {
                "personId": 1629004,
                "firstName": "Svi",
                "familyName": "Mykhailiuk",
                "nameI": "S. Mykhailiuk",
                "playerSlug": "svi-mykhailiuk",
                "position": "",
                "comment": "DNP - Coach's Decision",
                "jerseyNum": "",
                "statistics": {
                    "minutes": "",
                    "fieldGoalsMade": 0,
                    "fieldGoalsAttempted": 0,
                    "fieldGoalsPercentage": 0,
                    "threePointersMade": 0,
                    "threePointersAttempted": 0,
                    "threePointersPercentage": 0,
                    "freeThrowsMade": 0,
                    "freeThrowsAttempted": 0,
                    "freeThrowsPercentage": 0,
                    "reboundsOffensive": 0,
                    "reboundsDefensive": 0,
                    "reboundsTotal": 0,
                    "assists": 0,
                    "steals": 0,
                    "blocks": 0,
                    "turnovers": 0,
                    "foulsPersonal": 0,
                    "points": 0,
                    "plusMinusPoints": 0
                }
            }
        ],
        "inactives": [
            {
                "personId": 1641809,
                "firstName": "Drew",
                "familyName": "Peterson",
                "jerseyNum": "13  "
            },
            {
                "personId": 1629674,
                "firstName": "Neemias",
                "familyName": "Queta",
                "jerseyNum": "88  "
            },
            {
                "personId": 1630531,
                "firstName": "Jaden",
                "familyName": "Springer",
                "jerseyNum": "44  "
            },
            {
                "personId": 1641775,
                "firstName": "Jordan",
                "familyName": "Walsh",
                "jerseyNum": "27  "
            },
            {
                "personId": 1631120,
                "firstName": "JD",
                "familyName": "Davison",
                "jerseyNum": "20  "
            }
        ],
        "starters": {
            "minutes": "202:11",
            "fieldGoalsMade": 39,
            "fieldGoalsAttempted": 81,
            "fieldGoalsPercentage": 0.481,
            "threePointersMade": 12,
            "threePointersAttempted": 29,
            "threePointersPercentage": 0.414,
            "freeThrowsMade": 14,
            "freeThrowsAttempted": 17,
            "freeThrowsPercentage": 0.824,
            "reboundsOffensive": 8,
            "reboundsDefensive": 27,
            "reboundsTotal": 35,
            "assists": 22,
            "steals": 5,
            "blocks": 6,
            "turnovers": 11,
            "foulsPersonal": 13,
            "points": 104
        },
        "bench": {
            "minutes": "202:11",
            "fieldGoalsMade": 5,
            "fieldGoalsAttempted": 10,
            "fieldGoalsPercentage": 0.5,
            "threePointersMade": 2,
            "threePointersAttempted": 5,
            "threePointersPercentage": 0.4,
            "freeThrowsMade": 4,
            "freeThrowsAttempted": 4,
            "freeThrowsPercentage": 1,
            "reboundsOffensive": 1,
            "reboundsDefensive": 5,
            "reboundsTotal": 6,
            "assists": 5,
            "steals": 2,
            "blocks": 0,
            "turnovers": 1,
            "foulsPersonal": 2,
            "points": 16
        }
    },
    "lastFiveMeetings": {
        "meetings": [
            {
                "recencyOrder": 1,
                "gameId": "0022301034",
                "gameTimeUTC": "2024-03-25T23:30:00Z",
                "gameEt": "2024-03-25T19:30:00Z",
                "gameStatus": 3,
                "gameStatusText": "Final",
                "gameClock": "PT00M00.00S",
                "awayTeam": {
                    "teamId": 1610612738,
                    "teamCity": "Boston",
                    "teamName": "Celtics",
                    "teamTricode": "BOS",
                    "teamSlug": "celtics",
                    "score": 118,
                    "wins": 57,
                    "losses": 15
                },
                "homeTeam": {
                    "teamId": 1610612737,
                    "teamCity": "Atlanta",
                    "teamName": "Hawks",
                    "teamTricode": "ATL",
                    "teamSlug": "hawks",
                    "score": 120,
                    "wins": 32,
                    "losses": 39
                }
            },
            {
                "recencyOrder": 2,
                "gameId": "0022300729",
                "gameTimeUTC": "2024-02-08T00:30:00Z",
                "gameEt": "2024-02-07T19:30:00Z",
                "gameStatus": 3,
                "gameStatusText": "Final",
                "gameClock": "PT00M00.00S",
                "awayTeam": {
                    "teamId": 1610612737,
                    "teamCity": "Atlanta",
                    "teamName": "Hawks",
                    "teamTricode": "ATL",
                    "teamSlug": "hawks",
                    "score": 117,
                    "wins": 22,
                    "losses": 29
                },
                "homeTeam": {
                    "teamId": 1610612738,
                    "teamCity": "Boston",
                    "teamName": "Celtics",
                    "teamTricode": "BOS",
                    "teamSlug": "celtics",
                    "score": 125,
                    "wins": 39,
                    "losses": 12
                }
            },
            {
                "recencyOrder": 3,
                "gameId": "0022300246",
                "gameTimeUTC": "2023-11-26T23:00:00Z",
                "gameEt": "2023-11-26T18:00:00Z",
                "gameStatus": 3,
                "gameStatusText": "Final",
                "gameClock": "PT00M00.00S",
                "awayTeam": {
                    "teamId": 1610612737,
                    "teamCity": "Atlanta",
                    "teamName": "Hawks",
                    "teamTricode": "ATL",
                    "teamSlug": "hawks",
                    "score": 103,
                    "wins": 8,
                    "losses": 8
                },
                "homeTeam": {
                    "teamId": 1610612738,
                    "teamCity": "Boston",
                    "teamName": "Celtics",
                    "teamTricode": "BOS",
                    "teamSlug": "celtics",
                    "score": 113,
                    "wins": 13,
                    "losses": 4
                }
            },
            {
                "recencyOrder": 4,
                "gameId": "0042200116",
                "gameTimeUTC": "2023-04-28T00:30:00Z",
                "gameEt": "2023-04-27T20:30:00Z",
                "gameStatus": 3,
                "gameStatusText": "Final",
                "gameClock": "PT00M00.00S",
                "awayTeam": {
                    "teamId": 1610612738,
                    "teamCity": "Boston",
                    "teamName": "Celtics",
                    "teamTricode": "BOS",
                    "teamSlug": "celtics",
                    "score": 128,
                    "wins": 4,
                    "losses": 2
                },
                "homeTeam": {
                    "teamId": 1610612737,
                    "teamCity": "Atlanta",
                    "teamName": "Hawks",
                    "teamTricode": "ATL",
                    "teamSlug": "hawks",
                    "score": 120,
                    "wins": 2,
                    "losses": 4
                }
            },
            {
                "recencyOrder": 5,
                "gameId": "0042200115",
                "gameTimeUTC": "2023-04-25T23:30:00Z",
                "gameEt": "2023-04-25T19:30:00Z",
                "gameStatus": 3,
                "gameStatusText": "Final",
                "gameClock": "PT00M00.00S",
                "awayTeam": {
                    "teamId": 1610612737,
                    "teamCity": "Atlanta",
                    "teamName": "Hawks",
                    "teamTricode": "ATL",
                    "teamSlug": "hawks",
                    "score": 119,
                    "wins": 2,
                    "losses": 3
                },
                "homeTeam": {
                    "teamId": 1610612738,
                    "teamCity": "Boston",
                    "teamName": "Celtics",
                    "teamTricode": "BOS",
                    "teamSlug": "celtics",
                    "score": 117,
                    "wins": 3,
                    "losses": 2
                }
            }
        ]
    },
    "pregameCharts": {
        "homeTeam": {
            "teamId": 1610612737,
            "teamCity": "Atlanta",
            "teamName": "Hawks",
            "teamTricode": "ATL",
            "statistics": {
                "points": 118.3,
                "reboundsTotal": 44.7,
                "assists": 26.6,
                "steals": 7.5,
                "blocks": 4.5,
                "turnovers": 12.8,
                "fieldGoalsPercentage": 0.465,
                "threePointersPercentage": 0.364,
                "freeThrowsPercentage": 0.797,
                "pointsInThePaint": 50.2,
                "pointsSecondChance": 15.8,
                "pointsFastBreak": 13.4,
                "playerPtsLeaderFirstName": "Dejounte",
                "playerPtsLeaderFamilyName": "Murray",
                "playerPtsLeaderId": 1627749,
                "playerPtsLeaderPts": 22.5,
                "playerRebLeaderFirstName": "Clint",
                "playerRebLeaderFamilyName": "Capela",
                "playerRebLeaderId": 203991,
                "playerRebLeaderReb": 10.6,
                "playerAstLeaderFirstName": "Dejounte",
                "playerAstLeaderFamilyName": "Murray",
                "playerAstLeaderId": 1627749,
                "playerAstLeaderAst": 6.4,
                "playerBlkLeaderFirstName": "Clint",
                "playerBlkLeaderFamilyName": "Capela",
                "playerBlkLeaderId": 203991,
                "playerBlkLeaderBlk": 1.45
            }
        },
        "awayTeam": {
            "teamId": 1610612738,
            "teamCity": "Boston",
            "teamName": "Celtics",
            "teamTricode": "BOS",
            "statistics": {
                "points": 120.6,
                "reboundsTotal": 46.3,
                "assists": 26.9,
                "steals": 6.8,
                "blocks": 6.6,
                "turnovers": 11.3,
                "fieldGoalsPercentage": 0.487,
                "threePointersPercentage": 0.388,
                "freeThrowsPercentage": 0.807,
                "pointsInThePaint": 47,
                "pointsSecondChance": 14.5,
                "pointsFastBreak": 15.3,
                "playerPtsLeaderFirstName": "Jayson",
                "playerPtsLeaderFamilyName": "Tatum",
                "playerPtsLeaderId": 1628369,
                "playerPtsLeaderPts": 26.9,
                "playerRebLeaderFirstName": "Jayson",
                "playerRebLeaderFamilyName": "Tatum",
                "playerRebLeaderId": 1628369,
                "playerRebLeaderReb": 8.1,
                "playerAstLeaderFirstName": "Derrick",
                "playerAstLeaderFamilyName": "White",
                "playerAstLeaderId": 1628401,
                "playerAstLeaderAst": 5.2,
                "playerBlkLeaderFirstName": "Derrick",
                "playerBlkLeaderFamilyName": "White",
                "playerBlkLeaderId": 1628401,
                "playerBlkLeaderBlk": 1.19
            }
        }
    },
    "postgameCharts": {
        "homeTeam": {
            "teamId": 1610612737,
            "teamCity": "Atlanta",
            "teamName": "Hawks",
            "teamTricode": "ATL",
            "statistics": {
                "points": 123,
                "reboundsTotal": 53,
                "assists": 24,
                "steals": 5,
                "blocks": 5,
                "turnovers": 11,
                "fieldGoalsPercentage": 0.49,
                "threePointersPercentage": 0.341,
                "freeThrowsPercentage": 0.6,
                "pointsInThePaint": 60,
                "pointsSecondChance": 28,
                "pointsFastBreak": 2,
                "biggestLead": 4,
                "leadChanges": 41,
                "timesTied": 14,
                "biggestScoringRun": 8,
                "turnoversTeam": 0,
                "turnoversTotal": 11,
                "reboundsTeam": 6,
                "pointsFromTurnovers": 15,
                "benchPoints": 20,
                "playerPtsLeaderFirstName": "Dejounte",
                "playerPtsLeaderFamilyName": "Murray",
                "playerPtsLeaderId": 1627749,
                "playerPtsLeaderPts": 44,
                "playerRebLeaderFirstName": "Clint",
                "playerRebLeaderFamilyName": "Capela",
                "playerRebLeaderId": 203991,
                "playerRebLeaderReb": 13,
                "playerAstLeaderFirstName": "Dejounte",
                "playerAstLeaderFamilyName": "Murray",
                "playerAstLeaderId": 1627749,
                "playerAstLeaderAst": 7,
                "playerBlkLeaderFirstName": "Clint",
                "playerBlkLeaderFamilyName": "Capela",
                "playerBlkLeaderId": 203991,
                "playerBlkLeaderBlk": 2
            }
        },
        "awayTeam": {
            "teamId": 1610612738,
            "teamCity": "Boston",
            "teamName": "Celtics",
            "teamTricode": "BOS",
            "statistics": {
                "points": 122,
                "reboundsTotal": 43,
                "assists": 28,
                "steals": 7,
                "blocks": 6,
                "turnovers": 12,
                "fieldGoalsPercentage": 0.479,
                "threePointersPercentage": 0.389,
                "freeThrowsPercentage": 0.857,
                "pointsInThePaint": 52,
                "pointsSecondChance": 11,
                "pointsFastBreak": 27,
                "biggestLead": 8,
                "leadChanges": 41,
                "timesTied": 14,
                "biggestScoringRun": 7,
                "turnoversTeam": 0,
                "turnoversTotal": 12,
                "reboundsTeam": 7,
                "pointsFromTurnovers": 11,
                "benchPoints": 18,
                "playerPtsLeaderFirstName": "Jayson",
                "playerPtsLeaderFamilyName": "Tatum",
                "playerPtsLeaderId": 1628369,
                "playerPtsLeaderPts": 31,
                "playerRebLeaderFirstName": "Jayson",
                "playerRebLeaderFamilyName": "Tatum",
                "playerRebLeaderId": 1628369,
                "playerRebLeaderReb": 13,
                "playerAstLeaderFirstName": "Jayson",
                "playerAstLeaderFamilyName": "Tatum",
                "playerAstLeaderId": 1628369,
                "playerAstLeaderAst": 6,
                "playerBlkLeaderFirstName": "Kristaps",
                "playerBlkLeaderFamilyName": "Porzingis",
                "playerBlkLeaderId": 204001,
                "playerBlkLeaderBlk": 3
            }
        }
    },
    "videoAvailableFlag": 1,
    "ptAvailable": 1,
    "ptXYZAvailable": 0,
    "whStatus": 1,
    "hustleStatus": 1,
    "historicalStatus": 0,
    "gameSubtype": "",
    "branchUrl": "https://nba.smart.link/2g4lj7g0e?gameid=1320405",
    "ogImage": "https://cdn.nba.com/davinci/images/team-matchups/nba/latest/web/bos-atl/1200x628.png",
    "hideLineScores": false,
    "hideGameCharts": false,
    "homeTeamPlayers": [
        {
            "personId": 1630249,
            "name": "Vit Krejci",
            "nameI": "V. Krejci",
            "firstName": "Vit",
            "familyName": "Krejci",
            "jerseyNum": "27"
        },
        {
            "personId": 203992,
            "name": "Bogdan Bogdanovic",
            "nameI": "B. Bogdanovic",
            "firstName": "Bogdan",
            "familyName": "Bogdanovic",
            "jerseyNum": "13"
        },
        {
            "personId": 203991,
            "name": "Clint Capela",
            "nameI": "C. Capela",
            "firstName": "Clint",
            "familyName": "Capela",
            "jerseyNum": "15"
        },
        {
            "personId": 1629685,
            "name": "Dylan Windler",
            "nameI": "D. Windler",
            "firstName": "Dylan",
            "familyName": "Windler",
            "jerseyNum": "20"
        },
        {
            "personId": 1629726,
            "name": "Garrison Mathews",
            "nameI": "G. Mathews",
            "firstName": "Garrison",
            "familyName": "Mathews",
            "jerseyNum": "25"
        },
        {
            "personId": 1627749,
            "name": "Dejounte Murray",
            "nameI": "D. Murray",
            "firstName": "Dejounte",
            "familyName": "Murray",
            "jerseyNum": "5"
        },
        {
            "personId": 202083,
            "name": "Wesley Matthews",
            "nameI": "W. Matthews",
            "firstName": "Wesley",
            "familyName": "Matthews",
            "jerseyNum": "32"
        },
        {
            "personId": 1628981,
            "name": "Bruno Fernando",
            "nameI": "B. Fernando",
            "firstName": "Bruno",
            "familyName": "Fernando",
            "jerseyNum": "24"
        },
        {
            "personId": 1630552,
            "name": "Jalen Johnson",
            "nameI": "J. Johnson",
            "firstName": "Jalen",
            "familyName": "Johnson",
            "jerseyNum": "1"
        },
        {
            "personId": 1630235,
            "name": "Trent Forrest",
            "nameI": "T. Forrest",
            "firstName": "Trent",
            "familyName": "Forrest",
            "jerseyNum": "2"
        },
        {
            "personId": 1629631,
            "name": "De'Andre Hunter",
            "nameI": "D. Hunter",
            "firstName": "De'Andre",
            "familyName": "Hunter",
            "jerseyNum": "12"
        },
        {
            "personId": 1629027,
            "name": "Trae Young",
            "nameI": "T. Young",
            "firstName": "Trae",
            "familyName": "Young",
            "jerseyNum": "11"
        }
    ],
    "awayTeamPlayers": [
        {
            "personId": 1629004,
            "name": "Svi Mykhailiuk",
            "nameI": "S. Mykhailiuk",
            "firstName": "Svi",
            "familyName": "Mykhailiuk",
            "jerseyNum": "50"
        },
        {
            "personId": 1630573,
            "name": "Sam Hauser",
            "nameI": "S. Hauser",
            "firstName": "Sam",
            "familyName": "Hauser",
            "jerseyNum": "30"
        },
        {
            "personId": 1630202,
            "name": "Payton Pritchard",
            "nameI": "P. Pritchard",
            "firstName": "Payton",
            "familyName": "Pritchard",
            "jerseyNum": "11"
        },
        {
            "personId": 1628401,
            "name": "Derrick White",
            "nameI": "D. White",
            "firstName": "Derrick",
            "familyName": "White",
            "jerseyNum": "9"
        },
        {
            "personId": 1629052,
            "name": "Oshae Brissett",
            "nameI": "O. Brissett",
            "firstName": "Oshae",
            "familyName": "Brissett",
            "jerseyNum": "12"
        },
        {
            "personId": 201143,
            "name": "Al Horford",
            "nameI": "A. Horford",
            "firstName": "Al",
            "familyName": "Horford",
            "jerseyNum": "42"
        },
        {
            "personId": 1630214,
            "name": "Xavier Tillman",
            "nameI": "X. Tillman",
            "firstName": "Xavier",
            "familyName": "Tillman",
            "jerseyNum": "26"
        },
        {
            "personId": 1628436,
            "name": "Luke Kornet",
            "nameI": "L. Kornet",
            "firstName": "Luke",
            "familyName": "Kornet",
            "jerseyNum": "40"
        },
        {
            "personId": 1627759,
            "name": "Jaylen Brown",
            "nameI": "J. Brown",
            "firstName": "Jaylen",
            "familyName": "Brown",
            "jerseyNum": "7"
        },
        {
            "personId": 201950,
            "name": "Jrue Holiday",
            "nameI": "J. Holiday",
            "firstName": "Jrue",
            "familyName": "Holiday",
            "jerseyNum": "4"
        },
        {
            "personId": 1628369,
            "name": "Jayson Tatum",
            "nameI": "J. Tatum",
            "firstName": "Jayson",
            "familyName": "Tatum",
            "jerseyNum": "0"
        },
        {
            "personId": 204001,
            "name": "Kristaps Porzingis",
            "nameI": "K. Porzingis",
            "firstName": "Kristaps",
            "familyName": "Porzingis",
            "jerseyNum": "8"
        }
    ],
    "hyperlinks": [],
    "pbOdds": {},
    "gameRecap": {
        "id": 1328751,
        "gameId": "0022301060",
        "title": "Game Recap: Hawks 123, Celtics 122",
        "permalink": "https://www.nba.com/watch/video/game-recap-hawks-123-celtics-122",
        "slug": "game-recap-hawks-123-celtics-122",
        "entitlements": "free",
        "videoDuration": "02:15",
        "excerpt": "Atlanta defeats Boston in OT, 123-122. For Atlanta, Dejounte Murray nails the game-winner and led the way with a career-high 44 points, seven rebounds, seven assists, and two steals with Bogdan Bogdanovic tallying 24 points, seven rebounds, and five assists while De\u2019Andre Hunter recorded 21 points and a career-high 13 rebounds in the victory. Jayson Tatum finished with 31 points, 13 rebounds, and six assists while aided by Kristaps Porzingis (20 points, seven rebounds, three blocks), and Derrick White (22 points, seven rebounds, five assists) for Boston in the losing effort. Atlanta improves to 34-39, while Boston moves to 57-16 in the loss.",
        "featuredImage": "https://cdn.nba.com/manage/2024/03/Full-Game-Highlights-Recap-YT-Thumbnail-23-24-BOS-ATL-RECAP.jpg"
    }
}